Workbook

Sheet READ ME
A1: What this workbook is
A3: A live re-computation of the equal-weight, fully-invested backtest from
A4: the Research OS engine. Every NAV, cost and metric is an Excel FORMULA,
A5: not a pasted number. Click any cell and read the formula bar.
A7: How to check the engine with it
A9: 1. On the 'Backtest' sheet, look at column W (NAV difference).
A10: That is Excel's NAV minus the engine's NAV, on every trading day.
A11: Every row should read 0.00E+00 or something around 1e-15.
A12: 2. The 'Metrics' sheet reports the largest difference across all rows.
A13: 3. Pick any rebalance row (column G = 1) and check by hand:
A14: traded (P) = sum over the five sleeves of
A15: |target weight - drifted weight|
... A43: and no amount of cross-checking retires them.

Sheet Prices
A1: Date | B1: NIFTY500 MOMENTUM 50 | C1: NIFTY500 QUALITY 50 | D1: NIFTY500 VALUE 50 | E1: NIFTY500 LOW VOLATILITY 50 | F1: NIFTY ALPHA 50
A2: 38443 | B2: 1000 | C2: 1000 | D2: 1000 | E2: 1000 | F2: 1589.39
A3: 38446 | B3: 1015.42 | C3: 996.81 | D3: 994.18 | E3: 1002.46 | F3: 1607.36
A4: 38447 | B4: 1008.76 | C4: 985.34 | D4: 980.92 | E4: 998.47 | F4: 1598.08
A5: 38448 | B5: 1025.13 | C5: 994.42 | D5: 1001.34 | E5: 1003.99 | F5: 1619.39
A6: 38449 | B6: 1019.09 | C6: 992.09 | D6: 1001.88 | E6: 999.23 | F6: 1622.37
A7: 38450 | B7: 1009.69 | C7: 982.17 | D7: 996.57 | E7: 989.93 | F7: 1605.66
A8: 38453 | B8: 999.58 | C8: 973.97 | D8: 990.16 | E8: 982.73 | F8: 1582.9
A9: 38454 | B9: 1005.32 | C9: 982.55 | D9: 996.6 | E9: 990.83 | F9: 1597.09
A10: 38455 | B10: 1005.21 | C10: 982.54 | D10: 997.5 | E10: 994.08 | F10: 1598.94
A11: 38457 | B11: 970.69 | C11: 948.26 | D11: 971.11 | E11: 970.63 | F11: 1552.51
A12: 38460 | B12: 958.05 | C12: 934.03 | D12: 965.13 | E12: 960.09 | F12: 1530.89
A13: 38461 | B13: 957.1 | C13: 922.97 | D13: 955.63 | E13: 956.23 | F13: 1526.52
... A5257: 46184 | B5257: 51363.45 | C5257: 18860.25 | D5257: 16046.6 | E5257: 21370.75 | F5257: 50749.5

Sheet Backtest
A1: Date | B1: Price: NIFTY500 MOMENTUM 50 | C1: Price: NIFTY500 QUALITY 50 | D1: Price: NIFTY500 VALUE 50 | E1: Price: NIFTY500 LOW VOLATILITY 50 | F1: Price: NIFTY ALPHA 50 | G1: Rebal? | H1: Started | I1: NAV before cost | J1: Units: NIFTY500 MOMENTUM 50 | K1: Units: NIFTY500 QUALITY 50 | L1: Units: NIFTY500 VALUE 50 | M1: Units: NIFTY500 LOW VOLATILITY 50 | N1: Units: NIFTY ALPHA 50 | O1: Cash | P1: Traded (L1) | Q1: Cost | R1: NAV | S1: Daily return | T1: Peak | U1: Drawdown | V1: ENGINE NAV | W1: NAV difference
A2: 38443 | B2: =Prices!B2 | C2: =Prices!C2 | D2: =Prices!D2 | E2: =Prices!E2 | F2: =Prices!F2 | G2: =IF(AND(0>=16,TEXT(A2,"yyyy-mm")<>TEXT(A3,"yyyy-mm")),1,0) | H2: =G2 | I2: 1 | J2: 0 | K2: 0 | L2: 0 | M2: 0 | N2: 0 | O2: 1 | P2: 0 | Q2: 0 | R2: 1 | S2: 0 | T2: 1 | U2: 0 | V2: 1 | W2: =R2-V2
A3: 38446 | B3: =Prices!B3 | C3: =Prices!C3 | D3: =Prices!D3 | E3: =Prices!E3 | F3: =Prices!F3 | G3: =IF(AND(1>=16,TEXT(A3,"yyyy-mm")<>TEXT(A4,"yyyy-mm")),1,0) | H3: =IF(OR(H2=1,G3=1),1,0) | I3: =IF(H2=0,1,SUMPRODUCT(J2:N2,B3:F3)+O2*(1+0.00023125256064071564)) | J3: =IF(G3=1,0.2*R3/B3,J2) | K3: =IF(G3=1,0.2*R3/C3,K2) | L3: =IF(G3=1,0.2*R3/D3,L2) | M3: =IF(G3=1,0.2*R3/E3,M2) | N3: =IF(G3=1,0.2*R3/F3,N2) | O3: =IF(G3=1,R3*(1-1.0),IF(H2=0,1,O2*(1+0.00023125256064071564))) | P3: =IF(G3=1,IF(H2=0,1,ABS(0.2-J2*B3/I3)+ABS(0.2-K2*C3/I3)+ABS(0.2-L2*D3/I3)+ABS(0.2-M2*E3/I3)+ABS(0.2-N2*F3/I3)),0) | Q3: =P3*0.0015 | R3: =I3*(1-Q3) | S3: =R3/R2-1 | T3: =MAX(T2,R3) | U3: =R3/T3-1 | V3: 1 | W3: =R3-V3
A4: 38447 | B4: =Prices!B4 | C4: =Prices!C4 | D4: =Prices!D4 | E4: =Prices!E4 | F4: =Prices!F4 | G4: =IF(AND(2>=16,TEXT(A4,"yyyy-mm")<>TEXT(A5,"yyyy-mm")),1,0) | H4: =IF(OR(H3=1,G4=1),1,0) | I4: =IF(H3=0,1,SUMPRODUCT(J3:N3,B4:F4)+O3*(1+0.00023125256064071564)) | J4: =IF(G4=1,0.2*R4/B4,J3) | K4: =IF(G4=1,0.2*R4/C4,K3) | L4: =IF(G4=1,0.2*R4/D4,L3) | M4: =IF(G4=1,0.2*R4/E4,M3) | N4: =IF(G4=1,0.2*R4/F4,N3) | O4: =IF(G4=1,R4*(1-1.0),IF(H3=0,1,O3*(1+0.00023125256064071564))) | P4: =IF(G4=1,IF(H3=0,1,ABS(0.2-J3*B4/I4)+ABS(0.2-K3*C4/I4)+ABS(0.2-L3*D4/I4)+ABS(0.2-M3*E4/I4)+ABS(0.2-N3*F4/I4)),0) | Q4: =P4*0.0015 | R4: =I4*(1-Q4) | S4: =R4/R3-1 | T4: =MAX(T3,R4) | U4: =R4/T4-1 | V4: 1 | W4: =R4-V4
A5: 38448 | B5: =Prices!B5 | C5: =Prices!C5 | D5: =Prices!D5 | E5: =Prices!E5 | F5: =Prices!F5 | G5: =IF(AND(3>=16,TEXT(A5,"yyyy-mm")<>TEXT(A6,"yyyy-mm")),1,0) | H5: =IF(OR(H4=1,G5=1),1,0) | I5: =IF(H4=0,1,SUMPRODUCT(J4:N4,B5:F5)+O4*(1+0.00023125256064071564)) | J5: =IF(G5=1,0.2*R5/B5,J4) | K5: =IF(G5=1,0.2*R5/C5,K4) | L5: =IF(G5=1,0.2*R5/D5,L4) | M5: =IF(G5=1,0.2*R5/E5,M4) | N5: =IF(G5=1,0.2*R5/F5,N4) | O5: =IF(G5=1,R5*(1-1.0),IF(H4=0,1,O4*(1+0.00023125256064071564))) | P5: =IF(G5=1,IF(H4=0,1,ABS(0.2-J4*B5/I5)+ABS(0.2-K4*C5/I5)+ABS(0.2-L4*D5/I5)+ABS(0.2-M4*E5/I5)+ABS(0.2-N4*F5/I5)),0) | Q5: =P5*0.0015 | R5: =I5*(1-Q5) | S5: =R5/R4-1 | T5: =MAX(T4,R5) | U5: =R5/T5-1 | V5: 1 | W5: =R5-V5
A6: 38449 | B6: =Prices!B6 | C6: =Prices!C6 | D6: =Prices!D6 | E6: =Prices!E6 | F6: =Prices!F6 | G6: =IF(AND(4>=16,TEXT(A6,"yyyy-mm")<>TEXT(A7,"yyyy-mm")),1,0) | H6: =IF(OR(H5=1,G6=1),1,0) | I6: =IF(H5=0,1,SUMPRODUCT(J5:N5,B6:F6)+O5*(1+0.00023125256064071564)) | J6: =IF(G6=1,0.2*R6/B6,J5) | K6: =IF(G6=1,0.2*R6/C6,K5) | L6: =IF(G6=1,0.2*R6/D6,L5) | M6: =IF(G6=1,0.2*R6/E6,M5) | N6: =IF(G6=1,0.2*R6/F6,N5) | O6: =IF(G6=1,R6*(1-1.0),IF(H5=0,1,O5*(1+0.00023125256064071564))) | P6: =IF(G6=1,IF(H5=0,1,ABS(0.2-J5*B6/I6)+ABS(0.2-K5*C6/I6)+ABS(0.2-L5*D6/I6)+ABS(0.2-M5*E6/I6)+ABS(0.2-N5*F6/I6)),0) | Q6: =P6*0.0015 | R6: =I6*(1-Q6) | S6: =R6/R5-1 | T6: =MAX(T5,R6) | U6: =R6/T6-1 | V6: 1 | W6: =R6-V6
A7: 38450 | B7: =Prices!B7 | C7: =Prices!C7 | D7: =Prices!D7 | E7: =Prices!E7 | F7: =Prices!F7 | G7: =IF(AND(5>=16,TEXT(A7,"yyyy-mm")<>TEXT(A8,"yyyy-mm")),1,0) | H7: =IF(OR(H6=1,G7=1),1,0) | I7: =IF(H6=0,1,SUMPRODUCT(J6:N6,B7:F7)+O6*(1+0.00023125256064071564)) | J7: =IF(G7=1,0.2*R7/B7,J6) | K7: =IF(G7=1,0.2*R7/C7,K6) | L7: =IF(G7=1,0.2*R7/D7,L6) | M7: =IF(G7=1,0.2*R7/E7,M6) | N7: =IF(G7=1,0.2*R7/F7,N6) | O7: =IF(G7=1,R7*(1-1.0),IF(H6=0,1,O6*(1+0.00023125256064071564))) | P7: =IF(G7=1,IF(H6=0,1,ABS(0.2-J6*B7/I7)+ABS(0.2-K6*C7/I7)+ABS(0.2-L6*D7/I7)+ABS(0.2-M6*E7/I7)+ABS(0.2-N6*F7/I7)),0) | Q7: =P7*0.0015 | R7: =I7*(1-Q7) | S7: =R7/R6-1 | T7: =MAX(T6,R7) | U7: =R7/T7-1 | V7: 1 | W7: =R7-V7
A8: 38453 | B8: =Prices!B8 | C8: =Prices!C8 | D8: =Prices!D8 | E8: =Prices!E8 | F8: =Prices!F8 | G8: =IF(AND(6>=16,TEXT(A8,"yyyy-mm")<>TEXT(A9,"yyyy-mm")),1,0) | H8: =IF(OR(H7=1,G8=1),1,0) | I8: =IF(H7=0,1,SUMPRODUCT(J7:N7,B8:F8)+O7*(1+0.00023125256064071564)) | J8: =IF(G8=1,0.2*R8/B8,J7) | K8: =IF(G8=1,0.2*R8/C8,K7) | L8: =IF(G8=1,0.2*R8/D8,L7) | M8: =IF(G8=1,0.2*R8/E8,M7) | N8: =IF(G8=1,0.2*R8/F8,N7) | O8: =IF(G8=1,R8*(1-1.0),IF(H7=0,1,O7*(1+0.00023125256064071564))) | P8: =IF(G8=1,IF(H7=0,1,ABS(0.2-J7*B8/I8)+ABS(0.2-K7*C8/I8)+ABS(0.2-L7*D8/I8)+ABS(0.2-M7*E8/I8)+ABS(0.2-N7*F8/I8)),0) | Q8: =P8*0.0015 | R8: =I8*(1-Q8) | S8: =R8/R7-1 | T8: =MAX(T7,R8) | U8: =R8/T8-1 | V8: 1 | W8: =R8-V8
A9: 38454 | B9: =Prices!B9 | C9: =Prices!C9 | D9: =Prices!D9 | E9: =Prices!E9 | F9: =Prices!F9 | G9: =IF(AND(7>=16,TEXT(A9,"yyyy-mm")<>TEXT(A10,"yyyy-mm")),1,0) | H9: =IF(OR(H8=1,G9=1),1,0) | I9: =IF(H8=0,1,SUMPRODUCT(J8:N8,B9:F9)+O8*(1+0.00023125256064071564)) | J9: =IF(G9=1,0.2*R9/B9,J8) | K9: =IF(G9=1,0.2*R9/C9,K8) | L9: =IF(G9=1,0.2*R9/D9,L8) | M9: =IF(G9=1,0.2*R9/E9,M8) | N9: =IF(G9=1,0.2*R9/F9,N8) | O9: =IF(G9=1,R9*(1-1.0),IF(H8=0,1,O8*(1+0.00023125256064071564))) | P9: =IF(G9=1,IF(H8=0,1,ABS(0.2-J8*B9/I9)+ABS(0.2-K8*C9/I9)+ABS(0.2-L8*D9/I9)+ABS(0.2-M8*E9/I9)+ABS(0.2-N8*F9/I9)),0) | Q9: =P9*0.0015 | R9: =I9*(1-Q9) | S9: =R9/R8-1 | T9: =MAX(T8,R9) | U9: =R9/T9-1 | V9: 1 | W9: =R9-V9
A10: 38455 | B10: =Prices!B10 | C10: =Prices!C10 | D10: =Prices!D10 | E10: =Prices!E10 | F10: =Prices!F10 | G10: =IF(AND(8>=16,TEXT(A10,"yyyy-mm")<>TEXT(A11,"yyyy-mm")),1,0) | H10: =IF(OR(H9=1,G10=1),1,0) | I10: =IF(H9=0,1,SUMPRODUCT(J9:N9,B10:F10)+O9*(1+0.00023125256064071564)) | J10: =IF(G10=1,0.2*R10/B10,J9) | K10: =IF(G10=1,0.2*R10/C10,K9) | L10: =IF(G10=1,0.2*R10/D10,L9) | M10: =IF(G10=1,0.2*R10/E10,M9) | N10: =IF(G10=1,0.2*R10/F10,N9) | O10: =IF(G10=1,R10*(1-1.0),IF(H9=0,1,O9*(1+0.00023125256064071564))) | P10: =IF(G10=1,IF(H9=0,1,ABS(0.2-J9*B10/I10)+ABS(0.2-K9*C10/I10)+ABS(0.2-L9*D10/I10)+ABS(0.2-M9*E10/I10)+ABS(0.2-N9*F10/I10)),0) | Q10: =P10*0.0015 | R10: =I10*(1-Q10) | S10: =R10/R9-1 | T10: =MAX(T9,R10) | U10: =R10/T10-1 | V10: 1 | W10: =R10-V10
A11: 38457 | B11: =Prices!B11 | C11: =Prices!C11 | D11: =Prices!D11 | E11: =Prices!E11 | F11: =Prices!F11 | G11: =IF(AND(9>=16,TEXT(A11,"yyyy-mm")<>TEXT(A12,"yyyy-mm")),1,0) | H11: =IF(OR(H10=1,G11=1),1,0) | I11: =IF(H10=0,1,SUMPRODUCT(J10:N10,B11:F11)+O10*(1+0.00023125256064071564)) | J11: =IF(G11=1,0.2*R11/B11,J10) | K11: =IF(G11=1,0.2*R11/C11,K10) | L11: =IF(G11=1,0.2*R11/D11,L10) | M11: =IF(G11=1,0.2*R11/E11,M10) | N11: =IF(G11=1,0.2*R11/F11,N10) | O11: =IF(G11=1,R11*(1-1.0),IF(H10=0,1,O10*(1+0.00023125256064071564))) | P11: =IF(G11=1,IF(H10=0,1,ABS(0.2-J10*B11/I11)+ABS(0.2-K10*C11/I11)+ABS(0.2-L10*D11/I11)+ABS(0.2-M10*E11/I11)+ABS(0.2-N10*F11/I11)),0) | Q11: =P11*0.0015 | R11: =I11*(1-Q11) | S11: =R11/R10-1 | T11: =MAX(T10,R11) | U11: =R11/T11-1 | V11: 1 | W11: =R11-V11
A12: 38460 | B12: =Prices!B12 | C12: =Prices!C12 | D12: =Prices!D12 | E12: =Prices!E12 | F12: =Prices!F12 | G12: =IF(AND(10>=16,TEXT(A12,"yyyy-mm")<>TEXT(A13,"yyyy-mm")),1,0) | H12: =IF(OR(H11=1,G12=1),1,0) | I12: =IF(H11=0,1,SUMPRODUCT(J11:N11,B12:F12)+O11*(1+0.00023125256064071564)) | J12: =IF(G12=1,0.2*R12/B12,J11) | K12: =IF(G12=1,0.2*R12/C12,K11) | L12: =IF(G12=1,0.2*R12/D12,L11) | M12: =IF(G12=1,0.2*R12/E12,M11) | N12: =IF(G12=1,0.2*R12/F12,N11) | O12: =IF(G12=1,R12*(1-1.0),IF(H11=0,1,O11*(1+0.00023125256064071564))) | P12: =IF(G12=1,IF(H11=0,1,ABS(0.2-J11*B12/I12)+ABS(0.2-K11*C12/I12)+ABS(0.2-L11*D12/I12)+ABS(0.2-M11*E12/I12)+ABS(0.2-N11*F12/I12)),0) | Q12: =P12*0.0015 | R12: =I12*(1-Q12) | S12: =R12/R11-1 | T12: =MAX(T11,R12) | U12: =R12/T12-1 | V12: 1 | W12: =R12-V12
A13: 38461 | B13: =Prices!B13 | C13: =Prices!C13 | D13: =Prices!D13 | E13: =Prices!E13 | F13: =Prices!F13 | G13: =IF(AND(11>=16,TEXT(A13,"yyyy-mm")<>TEXT(A14,"yyyy-mm")),1,0) | H13: =IF(OR(H12=1,G13=1),1,0) | I13: =IF(H12=0,1,SUMPRODUCT(J12:N12,B13:F13)+O12*(1+0.00023125256064071564)) | J13: =IF(G13=1,0.2*R13/B13,J12) | K13: =IF(G13=1,0.2*R13/C13,K12) | L13: =IF(G13=1,0.2*R13/D13,L12) | M13: =IF(G13=1,0.2*R13/E13,M12) | N13: =IF(G13=1,0.2*R13/F13,N12) | O13: =IF(G13=1,R13*(1-1.0),IF(H12=0,1,O12*(1+0.00023125256064071564))) | P13: =IF(G13=1,IF(H12=0,1,ABS(0.2-J12*B13/I13)+ABS(0.2-K12*C13/I13)+ABS(0.2-L12*D13/I13)+ABS(0.2-M12*E13/I13)+ABS(0.2-N12*F13/I13)),0) | Q13: =P13*0.0015 | R13: =I13*(1-Q13) | S13: =R13/R12-1 | T13: =MAX(T12,R13) | U13: =R13/T13-1 | V13: 1 | W13: =R13-V13
A14: 38462 | B14: =Prices!B14 | C14: =Prices!C14 | D14: =Prices!D14 | E14: =Prices!E14 | F14: =Prices!F14 | G14: =IF(AND(12>=16,TEXT(A14,"yyyy-mm")<>TEXT(A15,"yyyy-mm")),1,0) | H14: =IF(OR(H13=1,G14=1),1,0) | I14: =IF(H13=0,1,SUMPRODUCT(J13:N13,B14:F14)+O13*(1+0.00023125256064071564)) | J14: =IF(G14=1,0.2*R14/B14,J13) | K14: =IF(G14=1,0.2*R14/C14,K13) | L14: =IF(G14=1,0.2*R14/D14,L13) | M14: =IF(G14=1,0.2*R14/E14,M13) | N14: =IF(G14=1,0.2*R14/F14,N13) | O14: =IF(G14=1,R14*(1-1.0),IF(H13=0,1,O13*(1+0.00023125256064071564))) | P14: =IF(G14=1,IF(H13=0,1,ABS(0.2-J13*B14/I14)+ABS(0.2-K13*C14/I14)+ABS(0.2-L13*D14/I14)+ABS(0.2-M13*E14/I14)+ABS(0.2-N13*F14/I14)),0) | Q14: =P14*0.0015 | R14: =I14*(1-Q14) | S14: =R14/R13-1 | T14: =MAX(T13,R14) | U14: =R14/T14-1 | V14: 1 | W14: =R14-V14
A15: 38463 | B15: =Prices!B15 | C15: =Prices!C15 | D15: =Prices!D15 | E15: =Prices!E15 | F15: =Prices!F15 | G15: =IF(AND(13>=16,TEXT(A15,"yyyy-mm")<>TEXT(A16,"yyyy-mm")),1,0) | H15: =IF(OR(H14=1,G15=1),1,0) | I15: =IF(H14=0,1,SUMPRODUCT(J14:N14,B15:F15)+O14*(1+0.00023125256064071564)) | J15: =IF(G15=1,0.2*R15/B15,J14) | K15: =IF(G15=1,0.2*R15/C15,K14) | L15: =IF(G15=1,0.2*R15/D15,L14) | M15: =IF(G15=1,0.2*R15/E15,M14) | N15: =IF(G15=1,0.2*R15/F15,N14) | O15: =IF(G15=1,R15*(1-1.0),IF(H14=0,1,O14*(1+0.00023125256064071564))) | P15: =IF(G15=1,IF(H14=0,1,ABS(0.2-J14*B15/I15)+ABS(0.2-K14*C15/I15)+ABS(0.2-L14*D15/I15)+ABS(0.2-M14*E15/I15)+ABS(0.2-N14*F15/I15)),0) | Q15: =P15*0.0015 | R15: =I15*(1-Q15) | S15: =R15/R14-1 | T15: =MAX(T14,R15) | U15: =R15/T15-1 | V15: 1 | W15: =R15-V15
A16: 38464 | B16: =Prices!B16 | C16: =Prices!C16 | D16: =Prices!D16 | E16: =Prices!E16 | F16: =Prices!F16 | G16: =IF(AND(14>=16,TEXT(A16,"yyyy-mm")<>TEXT(A17,"yyyy-mm")),1,0) | H16: =IF(OR(H15=1,G16=1),1,0) | I16: =IF(H15=0,1,SUMPRODUCT(J15:N15,B16:F16)+O15*(1+0.00023125256064071564)) | J16: =IF(G16=1,0.2*R16/B16,J15) | K16: =IF(G16=1,0.2*R16/C16,K15) | L16: =IF(G16=1,0.2*R16/D16,L15) | M16: =IF(G16=1,0.2*R16/E16,M15) | N16: =IF(G16=1,0.2*R16/F16,N15) | O16: =IF(G16=1,R16*(1-1.0),IF(H15=0,1,O15*(1+0.00023125256064071564))) | P16: =IF(G16=1,IF(H15=0,1,ABS(0.2-J15*B16/I16)+ABS(0.2-K15*C16/I16)+ABS(0.2-L15*D16/I16)+ABS(0.2-M15*E16/I16)+ABS(0.2-N15*F16/I16)),0) | Q16: =P16*0.0015 | R16: =I16*(1-Q16) | S16: =R16/R15-1 | T16: =MAX(T15,R16) | U16: =R16/T16-1 | V16: 1 | W16: =R16-V16
A17: 38467 | B17: =Prices!B17 | C17: =Prices!C17 | D17: =Prices!D17 | E17: =Prices!E17 | F17: =Prices!F17 | G17: =IF(AND(15>=16,TEXT(A17,"yyyy-mm")<>TEXT(A18,"yyyy-mm")),1,0) | H17: =IF(OR(H16=1,G17=1),1,0) | I17: =IF(H16=0,1,SUMPRODUCT(J16:N16,B17:F17)+O16*(1+0.00023125256064071564)) | J17: =IF(G17=1,0.2*R17/B17,J16) | K17: =IF(G17=1,0.2*R17/C17,K16) | L17: =IF(G17=1,0.2*R17/D17,L16) | M17: =IF(G17=1,0.2*R17/E17,M16) | N17: =IF(G17=1,0.2*R17/F17,N16) | O17: =IF(G17=1,R17*(1-1.0),IF(H16=0,1,O16*(1+0.00023125256064071564))) | P17: =IF(G17=1,IF(H16=0,1,ABS(0.2-J16*B17/I17)+ABS(0.2-K16*C17/I17)+ABS(0.2-L16*D17/I17)+ABS(0.2-M16*E17/I17)+ABS(0.2-N16*F17/I17)),0) | Q17: =P17*0.0015 | R17: =I17*(1-Q17) | S17: =R17/R16-1 | T17: =MAX(T16,R17) | U17: =R17/T17-1 | V17: 1 | W17: =R17-V17
A18: 38468 | B18: =Prices!B18 | C18: =Prices!C18 | D18: =Prices!D18 | E18: =Prices!E18 | F18: =Prices!F18 | G18: =IF(AND(16>=16,TEXT(A18,"yyyy-mm")<>TEXT(A19,"yyyy-mm")),1,0) | H18: =IF(OR(H17=1,G18=1),1,0) | I18: =IF(H17=0,1,SUMPRODUCT(J17:N17,B18:F18)+O17*(1+0.00023125256064071564)) | J18: =IF(G18=1,0.2*R18/B18,J17) | K18: =IF(G18=1,0.2*R18/C18,K17) | L18: =IF(G18=1,0.2*R18/D18,L17) | M18: =IF(G18=1,0.2*R18/E18,M17) | N18: =IF(G18=1,0.2*R18/F18,N17) | O18: =IF(G18=1,R18*(1-1.0),IF(H17=0,1,O17*(1+0.00023125256064071564))) | P18: =IF(G18=1,IF(H17=0,1,ABS(0.2-J17*B18/I18)+ABS(0.2-K17*C18/I18)+ABS(0.2-L17*D18/I18)+ABS(0.2-M17*E18/I18)+ABS(0.2-N17*F18/I18)),0) | Q18: =P18*0.0015 | R18: =I18*(1-Q18) | S18: =R18/R17-1 | T18: =MAX(T17,R18) | U18: =R18/T18-1 | V18: 1 | W18: =R18-V18
A19: 38469 | B19: =Prices!B19 | C19: =Prices!C19 | D19: =Prices!D19 | E19: =Prices!E19 | F19: =Prices!F19 | G19: =IF(AND(17>=16,TEXT(A19,"yyyy-mm")<>TEXT(A20,"yyyy-mm")),1,0) | H19: =IF(OR(H18=1,G19=1),1,0) | I19: =IF(H18=0,1,SUMPRODUCT(J18:N18,B19:F19)+O18*(1+0.00023125256064071564)) | J19: =IF(G19=1,0.2*R19/B19,J18) | K19: =IF(G19=1,0.2*R19/C19,K18) | L19: =IF(G19=1,0.2*R19/D19,L18) | M19: =IF(G19=1,0.2*R19/E19,M18) | N19: =IF(G19=1,0.2*R19/F19,N18) | O19: =IF(G19=1,R19*(1-1.0),IF(H18=0,1,O18*(1+0.00023125256064071564))) | P19: =IF(G19=1,IF(H18=0,1,ABS(0.2-J18*B19/I19)+ABS(0.2-K18*C19/I19)+ABS(0.2-L18*D19/I19)+ABS(0.2-M18*E19/I19)+ABS(0.2-N18*F19/I19)),0) | Q19: =P19*0.0015 | R19: =I19*(1-Q19) | S19: =R19/R18-1 | T19: =MAX(T18,R19) | U19: =R19/T19-1 | V19: 1 | W19: =R19-V19
A20: 38470 | B20: =Prices!B20 | C20: =Prices!C20 | D20: =Prices!D20 | E20: =Prices!E20 | F20: =Prices!F20 | G20: =IF(AND(18>=16,TEXT(A20,"yyyy-mm")<>TEXT(A21,"yyyy-mm")),1,0) | H20: =IF(OR(H19=1,G20=1),1,0) | I20: =IF(H19=0,1,SUMPRODUCT(J19:N19,B20:F20)+O19*(1+0.00023125256064071564)) | J20: =IF(G20=1,0.2*R20/B20,J19) | K20: =IF(G20=1,0.2*R20/C20,K19) | L20: =IF(G20=1,0.2*R20/D20,L19) | M20: =IF(G20=1,0.2*R20/E20,M19) | N20: =IF(G20=1,0.2*R20/F20,N19) | O20: =IF(G20=1,R20*(1-1.0),IF(H19=0,1,O19*(1+0.00023125256064071564))) | P20: =IF(G20=1,IF(H19=0,1,ABS(0.2-J19*B20/I20)+ABS(0.2-K19*C20/I20)+ABS(0.2-L19*D20/I20)+ABS(0.2-M19*E20/I20)+ABS(0.2-N19*F20/I20)),0) | Q20: =P20*0.0015 | R20: =I20*(1-Q20) | S20: =R20/R19-1 | T20: =MAX(T19,R20) | U20: =R20/T20-1 | V20: 1 | W20: =R20-V20
A21: 38471 | B21: =Prices!B21 | C21: =Prices!C21 | D21: =Prices!D21 | E21: =Prices!E21 | F21: =Prices!F21 | G21: =IF(AND(19>=16,TEXT(A21,"yyyy-mm")<>TEXT(A22,"yyyy-mm")),1,0) | H21: =IF(OR(H20=1,G21=1),1,0) | I21: =IF(H20=0,1,SUMPRODUCT(J20:N20,B21:F21)+O20*(1+0.00023125256064071564)) | J21: =IF(G21=1,0.2*R21/B21,J20) | K21: =IF(G21=1,0.2*R21/C21,K20) | L21: =IF(G21=1,0.2*R21/D21,L20) | M21: =IF(G21=1,0.2*R21/E21,M20) | N21: =IF(G21=1,0.2*R21/F21,N20) | O21: =IF(G21=1,R21*(1-1.0),IF(H20=0,1,O20*(1+0.00023125256064071564))) | P21: =IF(G21=1,IF(H20=0,1,ABS(0.2-J20*B21/I21)+ABS(0.2-K20*C21/I21)+ABS(0.2-L20*D21/I21)+ABS(0.2-M20*E21/I21)+ABS(0.2-N20*F21/I21)),0) | Q21: =P21*0.0015 | R21: =I21*(1-Q21) | S21: =R21/R20-1 | T21: =MAX(T20,R21) | U21: =R21/T21-1 | V21: 0.9985 | W21: =R21-V21
A22: 38474 | B22: =Prices!B22 | C22: =Prices!C22 | D22: =Prices!D22 | E22: =Prices!E22 | F22: =Prices!F22 | G22: =IF(AND(20>=16,TEXT(A22,"yyyy-mm")<>TEXT(A23,"yyyy-mm")),1,0) | H22: =IF(OR(H21=1,G22=1),1,0) | I22: =IF(H21=0,1,SUMPRODUCT(J21:N21,B22:F22)+O21*(1+0.00023125256064071564)) | J22: =IF(G22=1,0.2*R22/B22,J21) | K22: =IF(G22=1,0.2*R22/C22,K21) | L22: =IF(G22=1,0.2*R22/D22,L21) | M22: =IF(G22=1,0.2*R22/E22,M21) | N22: =IF(G22=1,0.2*R22/F22,N21) | O22: =IF(G22=1,R22*(1-1.0),IF(H21=0,1,O21*(1+0.00023125256064071564))) | P22: =IF(G22=1,IF(H21=0,1,ABS(0.2-J21*B22/I22)+ABS(0.2-K21*C22/I22)+ABS(0.2-L21*D22/I22)+ABS(0.2-M21*E22/I22)+ABS(0.2-N21*F22/I22)),0) | Q22: =P22*0.0015 | R22: =I22*(1-Q22) | S22: =R22/R21-1 | T22: =MAX(T21,R22) | U22: =R22/T22-1 | V22: 0.99698393 | W22: =R22-V22
A23: 38475 | B23: =Prices!B23 | C23: =Prices!C23 | D23: =Prices!D23 | E23: =Prices!E23 | F23: =Prices!F23 | G23: =IF(AND(21>=16,TEXT(A23,"yyyy-mm")<>TEXT(A24,"yyyy-mm")),1,0) | H23: =IF(OR(H22=1,G23=1),1,0) | I23: =IF(H22=0,1,SUMPRODUCT(J22:N22,B23:F23)+O22*(1+0.00023125256064071564)) | J23: =IF(G23=1,0.2*R23/B23,J22) | K23: =IF(G23=1,0.2*R23/C23,K22) | L23: =IF(G23=1,0.2*R23/D23,L22) | M23: =IF(G23=1,0.2*R23/E23,M22) | N23: =IF(G23=1,0.2*R23/F23,N22) | O23: =IF(G23=1,R23*(1-1.0),IF(H22=0,1,O22*(1+0.00023125256064071564))) | P23: =IF(G23=1,IF(H22=0,1,ABS(0.2-J22*B23/I23)+ABS(0.2-K22*C23/I23)+ABS(0.2-L22*D23/I23)+ABS(0.2-M22*E23/I23)+ABS(0.2-N22*F23/I23)),0) | Q23: =P23*0.0015 | R23: =I23*(1-Q23) | S23: =R23/R22-1 | T23: =MAX(T22,R23) | U23: =R23/T23-1 | V23: 0.99897922 | W23: =R23-V23
A24: 38476 | B24: =Prices!B24 | C24: =Prices!C24 | D24: =Prices!D24 | E24: =Prices!E24 | F24: =Prices!F24 | G24: =IF(AND(22>=16,TEXT(A24,"yyyy-mm")<>TEXT(A25,"yyyy-mm")),1,0) | H24: =IF(OR(H23=1,G24=1),1,0) | I24: =IF(H23=0,1,SUMPRODUCT(J23:N23,B24:F24)+O23*(1+0.00023125256064071564)) | J24: =IF(G24=1,0.2*R24/B24,J23) | K24: =IF(G24=1,0.2*R24/C24,K23) | L24: =IF(G24=1,0.2*R24/D24,L23) | M24: =IF(G24=1,0.2*R24/E24,M23) | N24: =IF(G24=1,0.2*R24/F24,N23) | O24: =IF(G24=1,R24*(1-1.0),IF(H23=0,1,O23*(1+0.00023125256064071564))) | P24: =IF(G24=1,IF(H23=0,1,ABS(0.2-J23*B24/I24)+ABS(0.2-K23*C24/I24)+ABS(0.2-L23*D24/I24)+ABS(0.2-M23*E24/I24)+ABS(0.2-N23*F24/I24)),0) | Q24: =P24*0.0015 | R24: =I24*(1-Q24) | S24: =R24/R23-1 | T24: =MAX(T23,R24) | U24: =R24/T24-1 | V24: 1.0138275 | W24: =R24-V24
A25: 38477 | B25: =Prices!B25 | C25: =Prices!C25 | D25: =Prices!D25 | E25: =Prices!E25 | F25: =Prices!F25 | G25: =IF(AND(23>=16,TEXT(A25,"yyyy-mm")<>TEXT(A26,"yyyy-mm")),1,0) | H25: =IF(OR(H24=1,G25=1),1,0) | I25: =IF(H24=0,1,SUMPRODUCT(J24:N24,B25:F25)+O24*(1+0.00023125256064071564)) | J25: =IF(G25=1,0.2*R25/B25,J24) | K25: =IF(G25=1,0.2*R25/C25,K24) | L25: =IF(G25=1,0.2*R25/D25,L24) | M25: =IF(G25=1,0.2*R25/E25,M24) | N25: =IF(G25=1,0.2*R25/F25,N24) | O25: =IF(G25=1,R25*(1-1.0),IF(H24=0,1,O24*(1+0.00023125256064071564))) | P25: =IF(G25=1,IF(H24=0,1,ABS(0.2-J24*B25/I25)+ABS(0.2-K24*C25/I25)+ABS(0.2-L24*D25/I25)+ABS(0.2-M24*E25/I25)+ABS(0.2-N24*F25/I25)),0) | Q25: =P25*0.0015 | R25: =I25*(1-Q25) | S25: =R25/R24-1 | T25: =MAX(T24,R25) | U25: =R25/T25-1 | V25: 1.0244485 | W25: =R25-V25
A26: 38478 | B26: =Prices!B26 | C26: =Prices!C26 | D26: =Prices!D26 | E26: =Prices!E26 | F26: =Prices!F26 | G26: =IF(AND(24>=16,TEXT(A26,"yyyy-mm")<>TEXT(A27,"yyyy-mm")),1,0) | H26: =IF(OR(H25=1,G26=1),1,0) | I26: =IF(H25=0,1,SUMPRODUCT(J25:N25,B26:F26)+O25*(1+0.00023125256064071564)) | J26: =IF(G26=1,0.2*R26/B26,J25) | K26: =IF(G26=1,0.2*R26/C26,K25) | L26: =IF(G26=1,0.2*R26/D26,L25) | M26: =IF(G26=1,0.2*R26/E26,M25) | N26: =IF(G26=1,0.2*R26/F26,N25) | O26: =IF(G26=1,R26*(1-1.0),IF(H25=0,1,O25*(1+0.00023125256064071564))) | P26: =IF(G26=1,IF(H25=0,1,ABS(0.2-J25*B26/I26)+ABS(0.2-K25*C26/I26)+ABS(0.2-L25*D26/I26)+ABS(0.2-M25*E26/I26)+ABS(0.2-N25*F26/I26)),0) | Q26: =P26*0.0015 | R26: =I26*(1-Q26) | S26: =R26/R25-1 | T26: =MAX(T25,R26) | U26: =R26/T26-1 | V26: 1.0295725 | W26: =R26-V26
A27: 38481 | B27: =Prices!B27 | C27: =Prices!C27 | D27: =Prices!D27 | E27: =Prices!E27 | F27: =Prices!F27 | G27: =IF(AND(25>=16,TEXT(A27,"yyyy-mm")<>TEXT(A28,"yyyy-mm")),1,0) | H27: =IF(OR(H26=1,G27=1),1,0) | I27: =IF(H26=0,1,SUMPRODUCT(J26:N26,B27:F27)+O26*(1+0.00023125256064071564)) | J27: =IF(G27=1,0.2*R27/B27,J26) | K27: =IF(G27=1,0.2*R27/C27,K26) | L27: =IF(G27=1,0.2*R27/D27,L26) | M27: =IF(G27=1,0.2*R27/E27,M26) | N27: =IF(G27=1,0.2*R27/F27,N26) | O27: =IF(G27=1,R27*(1-1.0),IF(H26=0,1,O26*(1+0.00023125256064071564))) | P27: =IF(G27=1,IF(H26=0,1,ABS(0.2-J26*B27/I27)+ABS(0.2-K26*C27/I27)+ABS(0.2-L26*D27/I27)+ABS(0.2-M26*E27/I27)+ABS(0.2-N26*F27/I27)),0) | Q27: =P27*0.0015 | R27: =I27*(1-Q27) | S27: =R27/R26-1 | T27: =MAX(T26,R27) | U27: =R27/T27-1 | V27: 1.0426492 | W27: =R27-V27
A28: 38482 | B28: =Prices!B28 | C28: =Prices!C28 | D28: =Prices!D28 | E28: =Prices!E28 | F28: =Prices!F28 | G28: =IF(AND(26>=16,TEXT(A28,"yyyy-mm")<>TEXT(A29,"yyyy-mm")),1,0) | H28: =IF(OR(H27=1,G28=1),1,0) | I28: =IF(H27=0,1,SUMPRODUCT(J27:N27,B28:F28)+O27*(1+0.00023125256064071564)) | J28: =IF(G28=1,0.2*R28/B28,J27) | K28: =IF(G28=1,0.2*R28/C28,K27) | L28: =IF(G28=1,0.2*R28/D28,L27) | M28: =IF(G28=1,0.2*R28/E28,M27) | N28: =IF(G28=1,0.2*R28/F28,N27) | O28: =IF(G28=1,R28*(1-1.0),IF(H27=0,1,O27*(1+0.00023125256064071564))) | P28: =IF(G28=1,IF(H27=0,1,ABS(0.2-J27*B28/I28)+ABS(0.2-K27*C28/I28)+ABS(0.2-L27*D28/I28)+ABS(0.2-M27*E28/I28)+ABS(0.2-N27*F28/I28)),0) | Q28: =P28*0.0015 | R28: =I28*(1-Q28) | S28: =R28/R27-1 | T28: =MAX(T27,R28) | U28: =R28/T28-1 | V28: 1.0406986 | W28: =R28-V28
A29: 38483 | B29: =Prices!B29 | C29: =Prices!C29 | D29: =Prices!D29 | E29: =Prices!E29 | F29: =Prices!F29 | G29: =IF(AND(27>=16,TEXT(A29,"yyyy-mm")<>TEXT(A30,"yyyy-mm")),1,0) | H29: =IF(OR(H28=1,G29=1),1,0) | I29: =IF(H28=0,1,SUMPRODUCT(J28:N28,B29:F29)+O28*(1+0.00023125256064071564)) | J29: =IF(G29=1,0.2*R29/B29,J28) | K29: =IF(G29=1,0.2*R29/C29,K28) | L29: =IF(G29=1,0.2*R29/D29,L28) | M29: =IF(G29=1,0.2*R29/E29,M28) | N29: =IF(G29=1,0.2*R29/F29,N28) | O29: =IF(G29=1,R29*(1-1.0),IF(H28=0,1,O28*(1+0.00023125256064071564))) | P29: =IF(G29=1,IF(H28=0,1,ABS(0.2-J28*B29/I29)+ABS(0.2-K28*C29/I29)+ABS(0.2-L28*D29/I29)+ABS(0.2-M28*E29/I29)+ABS(0.2-N28*F29/I29)),0) | Q29: =P29*0.0015 | R29: =I29*(1-Q29) | S29: =R29/R28-1 | T29: =MAX(T28,R29) | U29: =R29/T29-1 | V29: 1.0396584 | W29: =R29-V29
A30: 38484 | B30: =Prices!B30 | C30: =Prices!C30 | D30: =Prices!D30 | E30: =Prices!E30 | F30: =Prices!F30 | G30: =IF(AND(28>=16,TEXT(A30,"yyyy-mm")<>TEXT(A31,"yyyy-mm")),1,0) | H30: =IF(OR(H29=1,G30=1),1,0) | I30: =IF(H29=0,1,SUMPRODUCT(J29:N29,B30:F30)+O29*(1+0.00023125256064071564)) | J30: =IF(G30=1,0.2*R30/B30,J29) | K30: =IF(G30=1,0.2*R30/C30,K29) | L30: =IF(G30=1,0.2*R30/D30,L29) | M30: =IF(G30=1,0.2*R30/E30,M29) | N30: =IF(G30=1,0.2*R30/F30,N29) | O30: =IF(G30=1,R30*(1-1.0),IF(H29=0,1,O29*(1+0.00023125256064071564))) | P30: =IF(G30=1,IF(H29=0,1,ABS(0.2-J29*B30/I30)+ABS(0.2-K29*C30/I30)+ABS(0.2-L29*D30/I30)+ABS(0.2-M29*E30/I30)+ABS(0.2-N29*F30/I30)),0) | Q30: =P30*0.0015 | R30: =I30*(1-Q30) | S30: =R30/R29-1 | T30: =MAX(T29,R30) | U30: =R30/T30-1 | V30: 1.0495132 | W30: =R30-V30
A31: 38485 | B31: =Prices!B31 | C31: =Prices!C31 | D31: =Prices!D31 | E31: =Prices!E31 | F31: =Prices!F31 | G31: =IF(AND(29>=16,TEXT(A31,"yyyy-mm")<>TEXT(A32,"yyyy-mm")),1,0) | H31: =IF(OR(H30=1,G31=1),1,0) | I31: =IF(H30=0,1,SUMPRODUCT(J30:N30,B31:F31)+O30*(1+0.00023125256064071564)) | J31: =IF(G31=1,0.2*R31/B31,J30) | K31: =IF(G31=1,0.2*R31/C31,K30) | L31: =IF(G31=1,0.2*R31/D31,L30) | M31: =IF(G31=1,0.2*R31/E31,M30) | N31: =IF(G31=1,0.2*R31/F31,N30) | O31: =IF(G31=1,R31*(1-1.0),IF(H30=0,1,O30*(1+0.00023125256064071564))) | P31: =IF(G31=1,IF(H30=0,1,ABS(0.2-J30*B31/I31)+ABS(0.2-K30*C31/I31)+ABS(0.2-L30*D31/I31)+ABS(0.2-M30*E31/I31)+ABS(0.2-N30*F31/I31)),0) | Q31: =P31*0.0015 | R31: =I31*(1-Q31) | S31: =R31/R30-1 | T31: =MAX(T30,R31) | U31: =R31/T31-1 | V31: 1.0539999 | W31: =R31-V31
A32: 38488 | B32: =Prices!B32 | C32: =Prices!C32 | D32: =Prices!D32 | E32: =Prices!E32 | F32: =Prices!F32 | G32: =IF(AND(30>=16,TEXT(A32,"yyyy-mm")<>TEXT(A33,"yyyy-mm")),1,0) | H32: =IF(OR(H31=1,G32=1),1,0) | I32: =IF(H31=0,1,SUMPRODUCT(J31:N31,B32:F32)+O31*(1+0.00023125256064071564)) | J32: =IF(G32=1,0.2*R32/B32,J31) | K32: =IF(G32=1,0.2*R32/C32,K31) | L32: =IF(G32=1,0.2*R32/D32,L31) | M32: =IF(G32=1,0.2*R32/E32,M31) | N32: =IF(G32=1,0.2*R32/F32,N31) | O32: =IF(G32=1,R32*(1-1.0),IF(H31=0,1,O31*(1+0.00023125256064071564))) | P32: =IF(G32=1,IF(H31=0,1,ABS(0.2-J31*B32/I32)+ABS(0.2-K31*C32/I32)+ABS(0.2-L31*D32/I32)+ABS(0.2-M31*E32/I32)+ABS(0.2-N31*F32/I32)),0) | Q32: =P32*0.0015 | R32: =I32*(1-Q32) | S32: =R32/R31-1 | T32: =MAX(T31,R32) | U32: =R32/T32-1 | V32: 1.0666264 | W32: =R32-V32
A33: 38489 | B33: =Prices!B33 | C33: =Prices!C33 | D33: =Prices!D33 | E33: =Prices!E33 | F33: =Prices!F33 | G33: =IF(AND(31>=16,TEXT(A33,"yyyy-mm")<>TEXT(A34,"yyyy-mm")),1,0) | H33: =IF(OR(H32=1,G33=1),1,0) | I33: =IF(H32=0,1,SUMPRODUCT(J32:N32,B33:F33)+O32*(1+0.00023125256064071564)) | J33: =IF(G33=1,0.2*R33/B33,J32) | K33: =IF(G33=1,0.2*R33/C33,K32) | L33: =IF(G33=1,0.2*R33/D33,L32) | M33: =IF(G33=1,0.2*R33/E33,M32) | N33: =IF(G33=1,0.2*R33/F33,N32) | O33: =IF(G33=1,R33*(1-1.0),IF(H32=0,1,O32*(1+0.00023125256064071564))) | P33: =IF(G33=1,IF(H32=0,1,ABS(0.2-J32*B33/I33)+ABS(0.2-K32*C33/I33)+ABS(0.2-L32*D33/I33)+ABS(0.2-M32*E33/I33)+ABS(0.2-N32*F33/I33)),0) | Q33: =P33*0.0015 | R33: =I33*(1-Q33) | S33: =R33/R32-1 | T33: =MAX(T32,R33) | U33: =R33/T33-1 | V33: 1.0557218 | W33: =R33-V33
A34: 38490 | B34: =Prices!B34 | C34: =Prices!C34 | D34: =Prices!D34 | E34: =Prices!E34 | F34: =Prices!F34 | G34: =IF(AND(32>=16,TEXT(A34,"yyyy-mm")<>TEXT(A35,"yyyy-mm")),1,0) | H34: =IF(OR(H33=1,G34=1),1,0) | I34: =IF(H33=0,1,SUMPRODUCT(J33:N33,B34:F34)+O33*(1+0.00023125256064071564)) | J34: =IF(G34=1,0.2*R34/B34,J33) | K34: =IF(G34=1,0.2*R34/C34,K33) | L34: =IF(G34=1,0.2*R34/D34,L33) | M34: =IF(G34=1,0.2*R34/E34,M33) | N34: =IF(G34=1,0.2*R34/F34,N33) | O34: =IF(G34=1,R34*(1-1.0),IF(H33=0,1,O33*(1+0.00023125256064071564))) | P34: =IF(G34=1,IF(H33=0,1,ABS(0.2-J33*B34/I34)+ABS(0.2-K33*C34/I34)+ABS(0.2-L33*D34/I34)+ABS(0.2-M33*E34/I34)+ABS(0.2-N33*F34/I34)),0) | Q34: =P34*0.0015 | R34: =I34*(1-Q34) | S34: =R34/R33-1 | T34: =MAX(T33,R34) | U34: =R34/T34-1 | V34: 1.0562474 | W34: =R34-V34
A35: 38491 | B35: =Prices!B35 | C35: =Prices!C35 | D35: =Prices!D35 | E35: =Prices!E35 | F35: =Prices!F35 | G35: =IF(AND(33>=16,TEXT(A35,"yyyy-mm")<>TEXT(A36,"yyyy-mm")),1,0) | H35: =IF(OR(H34=1,G35=1),1,0) | I35: =IF(H34=0,1,SUMPRODUCT(J34:N34,B35:F35)+O34*(1+0.00023125256064071564)) | J35: =IF(G35=1,0.2*R35/B35,J34) | K35: =IF(G35=1,0.2*R35/C35,K34) | L35: =IF(G35=1,0.2*R35/D35,L34) | M35: =IF(G35=1,0.2*R35/E35,M34) | N35: =IF(G35=1,0.2*R35/F35,N34) | O35: =IF(G35=1,R35*(1-1.0),IF(H34=0,1,O34*(1+0.00023125256064071564))) | P35: =IF(G35=1,IF(H34=0,1,ABS(0.2-J34*B35/I35)+ABS(0.2-K34*C35/I35)+ABS(0.2-L34*D35/I35)+ABS(0.2-M34*E35/I35)+ABS(0.2-N34*F35/I35)),0) | Q35: =P35*0.0015 | R35: =I35*(1-Q35) | S35: =R35/R34-1 | T35: =MAX(T34,R35) | U35: =R35/T35-1 | V35: 1.0643816 | W35: =R35-V35
A36: 38492 | B36: =Prices!B36 | C36: =Prices!C36 | D36: =Prices!D36 | E36: =Prices!E36 | F36: =Prices!F36 | G36: =IF(AND(34>=16,TEXT(A36,"yyyy-mm")<>TEXT(A37,"yyyy-mm")),1,0) | H36: =IF(OR(H35=1,G36=1),1,0) | I36: =IF(H35=0,1,SUMPRODUCT(J35:N35,B36:F36)+O35*(1+0.00023125256064071564)) | J36: =IF(G36=1,0.2*R36/B36,J35) | K36: =IF(G36=1,0.2*R36/C36,K35) | L36: =IF(G36=1,0.2*R36/D36,L35) | M36: =IF(G36=1,0.2*R36/E36,M35) | N36: =IF(G36=1,0.2*R36/F36,N35) | O36: =IF(G36=1,R36*(1-1.0),IF(H35=0,1,O35*(1+0.00023125256064071564))) | P36: =IF(G36=1,IF(H35=0,1,ABS(0.2-J35*B36/I36)+ABS(0.2-K35*C36/I36)+ABS(0.2-L35*D36/I36)+ABS(0.2-M35*E36/I36)+ABS(0.2-N35*F36/I36)),0) | Q36: =P36*0.0015 | R36: =I36*(1-Q36) | S36: =R36/R35-1 | T36: =MAX(T35,R36) | U36: =R36/T36-1 | V36: 1.063549 | W36: =R36-V36
A37: 38495 | B37: =Prices!B37 | C37: =Prices!C37 | D37: =Prices!D37 | E37: =Prices!E37 | F37: =Prices!F37 | G37: =IF(AND(35>=16,TEXT(A37,"yyyy-mm")<>TEXT(A38,"yyyy-mm")),1,0) | H37: =IF(OR(H36=1,G37=1),1,0) | I37: =IF(H36=0,1,SUMPRODUCT(J36:N36,B37:F37)+O36*(1+0.00023125256064071564)) | J37: =IF(G37=1,0.2*R37/B37,J36) | K37: =IF(G37=1,0.2*R37/C37,K36) | L37: =IF(G37=1,0.2*R37/D37,L36) | M37: =IF(G37=1,0.2*R37/E37,M36) | N37: =IF(G37=1,0.2*R37/F37,N36) | O37: =IF(G37=1,R37*(1-1.0),IF(H36=0,1,O36*(1+0.00023125256064071564))) | P37: =IF(G37=1,IF(H36=0,1,ABS(0.2-J36*B37/I37)+ABS(0.2-K36*C37/I37)+ABS(0.2-L36*D37/I37)+ABS(0.2-M36*E37/I37)+ABS(0.2-N36*F37/I37)),0) | Q37: =P37*0.0015 | R37: =I37*(1-Q37) | S37: =R37/R36-1 | T37: =MAX(T36,R37) | U37: =R37/T37-1 | V37: 1.0701266 | W37: =R37-V37
A38: 38496 | B38: =Prices!B38 | C38: =Prices!C38 | D38: =Prices!D38 | E38: =Prices!E38 | F38: =Prices!F38 | G38: =IF(AND(36>=16,TEXT(A38,"yyyy-mm")<>TEXT(A39,"yyyy-mm")),1,0) | H38: =IF(OR(H37=1,G38=1),1,0) | I38: =IF(H37=0,1,SUMPRODUCT(J37:N37,B38:F38)+O37*(1+0.00023125256064071564)) | J38: =IF(G38=1,0.2*R38/B38,J37) | K38: =IF(G38=1,0.2*R38/C38,K37) | L38: =IF(G38=1,0.2*R38/D38,L37) | M38: =IF(G38=1,0.2*R38/E38,M37) | N38: =IF(G38=1,0.2*R38/F38,N37) | O38: =IF(G38=1,R38*(1-1.0),IF(H37=0,1,O37*(1+0.00023125256064071564))) | P38: =IF(G38=1,IF(H37=0,1,ABS(0.2-J37*B38/I38)+ABS(0.2-K37*C38/I38)+ABS(0.2-L37*D38/I38)+ABS(0.2-M37*E38/I38)+ABS(0.2-N37*F38/I38)),0) | Q38: =P38*0.0015 | R38: =I38*(1-Q38) | S38: =R38/R37-1 | T38: =MAX(T37,R38) | U38: =R38/T38-1 | V38: 1.0745958 | W38: =R38-V38
A39: 38497 | B39: =Prices!B39 | C39: =Prices!C39 | D39: =Prices!D39 | E39: =Prices!E39 | F39: =Prices!F39 | G39: =IF(AND(37>=16,TEXT(A39,"yyyy-mm")<>TEXT(A40,"yyyy-mm")),1,0) | H39: =IF(OR(H38=1,G39=1),1,0) | I39: =IF(H38=0,1,SUMPRODUCT(J38:N38,B39:F39)+O38*(1+0.00023125256064071564)) | J39: =IF(G39=1,0.2*R39/B39,J38) | K39: =IF(G39=1,0.2*R39/C39,K38) | L39: =IF(G39=1,0.2*R39/D39,L38) | M39: =IF(G39=1,0.2*R39/E39,M38) | N39: =IF(G39=1,0.2*R39/F39,N38) | O39: =IF(G39=1,R39*(1-1.0),IF(H38=0,1,O38*(1+0.00023125256064071564))) | P39: =IF(G39=1,IF(H38=0,1,ABS(0.2-J38*B39/I39)+ABS(0.2-K38*C39/I39)+ABS(0.2-L38*D39/I39)+ABS(0.2-M38*E39/I39)+ABS(0.2-N38*F39/I39)),0) | Q39: =P39*0.0015 | R39: =I39*(1-Q39) | S39: =R39/R38-1 | T39: =MAX(T38,R39) | U39: =R39/T39-1 | V39: 1.0797647 | W39: =R39-V39
A40: 38498 | B40: =Prices!B40 | C40: =Prices!C40 | D40: =Prices!D40 | E40: =Prices!E40 | F40: =Prices!F40 | G40: =IF(AND(38>=16,TEXT(A40,"yyyy-mm")<>TEXT(A41,"yyyy-mm")),1,0) | H40: =IF(OR(H39=1,G40=1),1,0) | I40: =IF(H39=0,1,SUMPRODUCT(J39:N39,B40:F40)+O39*(1+0.00023125256064071564)) | J40: =IF(G40=1,0.2*R40/B40,J39) | K40: =IF(G40=1,0.2*R40/C40,K39) | L40: =IF(G40=1,0.2*R40/D40,L39) | M40: =IF(G40=1,0.2*R40/E40,M39) | N40: =IF(G40=1,0.2*R40/F40,N39) | O40: =IF(G40=1,R40*(1-1.0),IF(H39=0,1,O39*(1+0.00023125256064071564))) | P40: =IF(G40=1,IF(H39=0,1,ABS(0.2-J39*B40/I40)+ABS(0.2-K39*C40/I40)+ABS(0.2-L39*D40/I40)+ABS(0.2-M39*E40/I40)+ABS(0.2-N39*F40/I40)),0) | Q40: =P40*0.0015 | R40: =I40*(1-Q40) | S40: =R40/R39-1 | T40: =MAX(T39,R40) | U40: =R40/T40-1 | V40: 1.0795379 | W40: =R40-V40
A41: 38499 | B41: =Prices!B41 | C41: =Prices!C41 | D41: =Prices!D41 | E41: =Prices!E41 | F41: =Prices!F41 | G41: =IF(AND(39>=16,TEXT(A41,"yyyy-mm")<>TEXT(A42,"yyyy-mm")),1,0) | H41: =IF(OR(H40=1,G41=1),1,0) | I41: =IF(H40=0,1,SUMPRODUCT(J40:N40,B41:F41)+O40*(1+0.00023125256064071564)) | J41: =IF(G41=1,0.2*R41/B41,J40) | K41: =IF(G41=1,0.2*R41/C41,K40) | L41: =IF(G41=1,0.2*R41/D41,L40) | M41: =IF(G41=1,0.2*R41/E41,M40) | N41: =IF(G41=1,0.2*R41/F41,N40) | O41: =IF(G41=1,R41*(1-1.0),IF(H40=0,1,O40*(1+0.00023125256064071564))) | P41: =IF(G41=1,IF(H40=0,1,ABS(0.2-J40*B41/I41)+ABS(0.2-K40*C41/I41)+ABS(0.2-L40*D41/I41)+ABS(0.2-M40*E41/I41)+ABS(0.2-N40*F41/I41)),0) | Q41: =P41*0.0015 | R41: =I41*(1-Q41) | S41: =R41/R40-1 | T41: =MAX(T40,R41) | U41: =R41/T41-1 | V41: 1.0790668 | W41: =R41-V41
A42: 38502 | B42: =Prices!B42 | C42: =Prices!C42 | D42: =Prices!D42 | E42: =Prices!E42 | F42: =Prices!F42 | G42: =IF(AND(40>=16,TEXT(A42,"yyyy-mm")<>TEXT(A43,"yyyy-mm")),1,0) | H42: =IF(OR(H41=1,G42=1),1,0) | I42: =IF(H41=0,1,SUMPRODUCT(J41:N41,B42:F42)+O41*(1+0.00023125256064071564)) | J42: =IF(G42=1,0.2*R42/B42,J41) | K42: =IF(G42=1,0.2*R42/C42,K41) | L42: =IF(G42=1,0.2*R42/D42,L41) | M42: =IF(G42=1,0.2*R42/E42,M41) | N42: =IF(G42=1,0.2*R42/F42,N41) | O42: =IF(G42=1,R42*(1-1.0),IF(H41=0,1,O41*(1+0.00023125256064071564))) | P42: =IF(G42=1,IF(H41=0,1,ABS(0.2-J41*B42/I42)+ABS(0.2-K41*C42/I42)+ABS(0.2-L41*D42/I42)+ABS(0.2-M41*E42/I42)+ABS(0.2-N41*F42/I42)),0) | Q42: =P42*0.0015 | R42: =I42*(1-Q42) | S42: =R42/R41-1 | T42: =MAX(T41,R42) | U42: =R42/T42-1 | V42: 1.0727221 | W42: =R42-V42
A43: 38503 | B43: =Prices!B43 | C43: =Prices!C43 | D43: =Prices!D43 | E43: =Prices!E43 | F43: =Prices!F43 | G43: =IF(AND(41>=16,TEXT(A43,"yyyy-mm")<>TEXT(A44,"yyyy-mm")),1,0) | H43: =IF(OR(H42=1,G43=1),1,0) | I43: =IF(H42=0,1,SUMPRODUCT(J42:N42,B43:F43)+O42*(1+0.00023125256064071564)) | J43: =IF(G43=1,0.2*R43/B43,J42) | K43: =IF(G43=1,0.2*R43/C43,K42) | L43: =IF(G43=1,0.2*R43/D43,L42) | M43: =IF(G43=1,0.2*R43/E43,M42) | N43: =IF(G43=1,0.2*R43/F43,N42) | O43: =IF(G43=1,R43*(1-1.0),IF(H42=0,1,O42*(1+0.00023125256064071564))) | P43: =IF(G43=1,IF(H42=0,1,ABS(0.2-J42*B43/I43)+ABS(0.2-K42*C43/I43)+ABS(0.2-L42*D43/I43)+ABS(0.2-M42*E43/I43)+ABS(0.2-N42*F43/I43)),0) | Q43: =P43*0.0015 | R43: =I43*(1-Q43) | S43: =R43/R42-1 | T43: =MAX(T42,R43) | U43: =R43/T43-1 | V43: 1.0795312 | W43: =R43-V43
A44: 38504 | B44: =Prices!B44 | C44: =Prices!C44 | D44: =Prices!D44 | E44: =Prices!E44 | F44: =Prices!F44 | G44: =IF(AND(42>=16,TEXT(A44,"yyyy-mm")<>TEXT(A45,"yyyy-mm")),1,0) | H44: =IF(OR(H43=1,G44=1),1,0) | I44: =IF(H43=0,1,SUMPRODUCT(J43:N43,B44:F44)+O43*(1+0.00023125256064071564)) | J44: =IF(G44=1,0.2*R44/B44,J43) | K44: =IF(G44=1,0.2*R44/C44,K43) | L44: =IF(G44=1,0.2*R44/D44,L43) | M44: =IF(G44=1,0.2*R44/E44,M43) | N44: =IF(G44=1,0.2*R44/F44,N43) | O44: =IF(G44=1,R44*(1-1.0),IF(H43=0,1,O43*(1+0.00023125256064071564))) | P44: =IF(G44=1,IF(H43=0,1,ABS(0.2-J43*B44/I44)+ABS(0.2-K43*C44/I44)+ABS(0.2-L43*D44/I44)+ABS(0.2-M43*E44/I44)+ABS(0.2-N43*F44/I44)),0) | Q44: =P44*0.0015 | R44: =I44*(1-Q44) | S44: =R44/R43-1 | T44: =MAX(T43,R44) | U44: =R44/T44-1 | V44: 1.0849882 | W44: =R44-V44
A45: 38505 | B45: =Prices!B45 | C45: =Prices!C45 | D45: =Prices!D45 | E45: =Prices!E45 | F45: =Prices!F45 | G45: =IF(AND(43>=16,TEXT(A45,"yyyy-mm")<>TEXT(A46,"yyyy-mm")),1,0) | H45: =IF(OR(H44=1,G45=1),1,0) | I45: =IF(H44=0,1,SUMPRODUCT(J44:N44,B45:F45)+O44*(1+0.00023125256064071564)) | J45: =IF(G45=1,0.2*R45/B45,J44) | K45: =IF(G45=1,0.2*R45/C45,K44) | L45: =IF(G45=1,0.2*R45/D45,L44) | M45: =IF(G45=1,0.2*R45/E45,M44) | N45: =IF(G45=1,0.2*R45/F45,N44) | O45: =IF(G45=1,R45*(1-1.0),IF(H44=0,1,O44*(1+0.00023125256064071564))) | P45: =IF(G45=1,IF(H44=0,1,ABS(0.2-J44*B45/I45)+ABS(0.2-K44*C45/I45)+ABS(0.2-L44*D45/I45)+ABS(0.2-M44*E45/I45)+ABS(0.2-N44*F45/I45)),0) | Q45: =P45*0.0015 | R45: =I45*(1-Q45) | S45: =R45/R44-1 | T45: =MAX(T44,R45) | U45: =R45/T45-1 | V45: 1.0776888 | W45: =R45-V45
A46: 38506 | B46: =Prices!B46 | C46: =Prices!C46 | D46: =Prices!D46 | E46: =Prices!E46 | F46: =Prices!F46 | G46: =IF(AND(44>=16,TEXT(A46,"yyyy-mm")<>TEXT(A47,"yyyy-mm")),1,0) | H46: =IF(OR(H45=1,G46=1),1,0) | I46: =IF(H45=0,1,SUMPRODUCT(J45:N45,B46:F46)+O45*(1+0.00023125256064071564)) | J46: =IF(G46=1,0.2*R46/B46,J45) | K46: =IF(G46=1,0.2*R46/C46,K45) | L46: =IF(G46=1,0.2*R46/D46,L45) | M46: =IF(G46=1,0.2*R46/E46,M45) | N46: =IF(G46=1,0.2*R46/F46,N45) | O46: =IF(G46=1,R46*(1-1.0),IF(H45=0,1,O45*(1+0.00023125256064071564))) | P46: =IF(G46=1,IF(H45=0,1,ABS(0.2-J45*B46/I46)+ABS(0.2-K45*C46/I46)+ABS(0.2-L45*D46/I46)+ABS(0.2-M45*E46/I46)+ABS(0.2-N45*F46/I46)),0) | Q46: =P46*0.0015 | R46: =I46*(1-Q46) | S46: =R46/R45-1 | T46: =MAX(T45,R46) | U46: =R46/T46-1 | V46: 1.0860741 | W46: =R46-V46
A47: 38507 | B47: =Prices!B47 | C47: =Prices!C47 | D47: =Prices!D47 | E47: =Prices!E47 | F47: =Prices!F47 | G47: =IF(AND(45>=16,TEXT(A47,"yyyy-mm")<>TEXT(A48,"yyyy-mm")),1,0) | H47: =IF(OR(H46=1,G47=1),1,0) | I47: =IF(H46=0,1,SUMPRODUCT(J46:N46,B47:F47)+O46*(1+0.00023125256064071564)) | J47: =IF(G47=1,0.2*R47/B47,J46) | K47: =IF(G47=1,0.2*R47/C47,K46) | L47: =IF(G47=1,0.2*R47/D47,L46) | M47: =IF(G47=1,0.2*R47/E47,M46) | N47: =IF(G47=1,0.2*R47/F47,N46) | O47: =IF(G47=1,R47*(1-1.0),IF(H46=0,1,O46*(1+0.00023125256064071564))) | P47: =IF(G47=1,IF(H46=0,1,ABS(0.2-J46*B47/I47)+ABS(0.2-K46*C47/I47)+ABS(0.2-L46*D47/I47)+ABS(0.2-M46*E47/I47)+ABS(0.2-N46*F47/I47)),0) | Q47: =P47*0.0015 | R47: =I47*(1-Q47) | S47: =R47/R46-1 | T47: =MAX(T46,R47) | U47: =R47/T47-1 | V47: 1.0915187 | W47: =R47-V47
A48: 38509 | B48: =Prices!B48 | C48: =Prices!C48 | D48: =Prices!D48 | E48: =Prices!E48 | F48: =Prices!F48 | G48: =IF(AND(46>=16,TEXT(A48,"yyyy-mm")<>TEXT(A49,"yyyy-mm")),1,0) | H48: =IF(OR(H47=1,G48=1),1,0) | I48: =IF(H47=0,1,SUMPRODUCT(J47:N47,B48:F48)+O47*(1+0.00023125256064071564)) | J48: =IF(G48=1,0.2*R48/B48,J47) | K48: =IF(G48=1,0.2*R48/C48,K47) | L48: =IF(G48=1,0.2*R48/D48,L47) | M48: =IF(G48=1,0.2*R48/E48,M47) | N48: =IF(G48=1,0.2*R48/F48,N47) | O48: =IF(G48=1,R48*(1-1.0),IF(H47=0,1,O47*(1+0.00023125256064071564))) | P48: =IF(G48=1,IF(H47=0,1,ABS(0.2-J47*B48/I48)+ABS(0.2-K47*C48/I48)+ABS(0.2-L47*D48/I48)+ABS(0.2-M47*E48/I48)+ABS(0.2-N47*F48/I48)),0) | Q48: =P48*0.0015 | R48: =I48*(1-Q48) | S48: =R48/R47-1 | T48: =MAX(T47,R48) | U48: =R48/T48-1 | V48: 1.0926434 | W48: =R48-V48
A49: 38510 | B49: =Prices!B49 | C49: =Prices!C49 | D49: =Prices!D49 | E49: =Prices!E49 | F49: =Prices!F49 | G49: =IF(AND(47>=16,TEXT(A49,"yyyy-mm")<>TEXT(A50,"yyyy-mm")),1,0) | H49: =IF(OR(H48=1,G49=1),1,0) | I49: =IF(H48=0,1,SUMPRODUCT(J48:N48,B49:F49)+O48*(1+0.00023125256064071564)) | J49: =IF(G49=1,0.2*R49/B49,J48) | K49: =IF(G49=1,0.2*R49/C49,K48) | L49: =IF(G49=1,0.2*R49/D49,L48) | M49: =IF(G49=1,0.2*R49/E49,M48) | N49: =IF(G49=1,0.2*R49/F49,N48) | O49: =IF(G49=1,R49*(1-1.0),IF(H48=0,1,O48*(1+0.00023125256064071564))) | P49: =IF(G49=1,IF(H48=0,1,ABS(0.2-J48*B49/I49)+ABS(0.2-K48*C49/I49)+ABS(0.2-L48*D49/I49)+ABS(0.2-M48*E49/I49)+ABS(0.2-N48*F49/I49)),0) | Q49: =P49*0.0015 | R49: =I49*(1-Q49) | S49: =R49/R48-1 | T49: =MAX(T48,R49) | U49: =R49/T49-1 | V49: 1.0974123 | W49: =R49-V49
A50: 38511 | B50: =Prices!B50 | C50: =Prices!C50 | D50: =Prices!D50 | E50: =Prices!E50 | F50: =Prices!F50 | G50: =IF(AND(48>=16,TEXT(A50,"yyyy-mm")<>TEXT(A51,"yyyy-mm")),1,0) | H50: =IF(OR(H49=1,G50=1),1,0) | I50: =IF(H49=0,1,SUMPRODUCT(J49:N49,B50:F50)+O49*(1+0.00023125256064071564)) | J50: =IF(G50=1,0.2*R50/B50,J49) | K50: =IF(G50=1,0.2*R50/C50,K49) | L50: =IF(G50=1,0.2*R50/D50,L49) | M50: =IF(G50=1,0.2*R50/E50,M49) | N50: =IF(G50=1,0.2*R50/F50,N49) | O50: =IF(G50=1,R50*(1-1.0),IF(H49=0,1,O49*(1+0.00023125256064071564))) | P50: =IF(G50=1,IF(H49=0,1,ABS(0.2-J49*B50/I50)+ABS(0.2-K49*C50/I50)+ABS(0.2-L49*D50/I50)+ABS(0.2-M49*E50/I50)+ABS(0.2-N49*F50/I50)),0) | Q50: =P50*0.0015 | R50: =I50*(1-Q50) | S50: =R50/R49-1 | T50: =MAX(T49,R50) | U50: =R50/T50-1 | V50: 1.1020706 | W50: =R50-V50
A51: 38512 | B51: =Prices!B51 | C51: =Prices!C51 | D51: =Prices!D51 | E51: =Prices!E51 | F51: =Prices!F51 | G51: =IF(AND(49>=16,TEXT(A51,"yyyy-mm")<>TEXT(A52,"yyyy-mm")),1,0) | H51: =IF(OR(H50=1,G51=1),1,0) | I51: =IF(H50=0,1,SUMPRODUCT(J50:N50,B51:F51)+O50*(1+0.00023125256064071564)) | J51: =IF(G51=1,0.2*R51/B51,J50) | K51: =IF(G51=1,0.2*R51/C51,K50) | L51: =IF(G51=1,0.2*R51/D51,L50) | M51: =IF(G51=1,0.2*R51/E51,M50) | N51: =IF(G51=1,0.2*R51/F51,N50) | O51: =IF(G51=1,R51*(1-1.0),IF(H50=0,1,O50*(1+0.00023125256064071564))) | P51: =IF(G51=1,IF(H50=0,1,ABS(0.2-J50*B51/I51)+ABS(0.2-K50*C51/I51)+ABS(0.2-L50*D51/I51)+ABS(0.2-M50*E51/I51)+ABS(0.2-N50*F51/I51)),0) | Q51: =P51*0.0015 | R51: =I51*(1-Q51) | S51: =R51/R50-1 | T51: =MAX(T50,R51) | U51: =R51/T51-1 | V51: 1.1034256 | W51: =R51-V51
A52: 38513 | B52: =Prices!B52 | C52: =Prices!C52 | D52: =Prices!D52 | E52: =Prices!E52 | F52: =Prices!F52 | G52: =IF(AND(50>=16,TEXT(A52,"yyyy-mm")<>TEXT(A53,"yyyy-mm")),1,0) | H52: =IF(OR(H51=1,G52=1),1,0) | I52: =IF(H51=0,1,SUMPRODUCT(J51:N51,B52:F52)+O51*(1+0.00023125256064071564)) | J52: =IF(G52=1,0.2*R52/B52,J51) | K52: =IF(G52=1,0.2*R52/C52,K51) | L52: =IF(G52=1,0.2*R52/D52,L51) | M52: =IF(G52=1,0.2*R52/E52,M51) | N52: =IF(G52=1,0.2*R52/F52,N51) | O52: =IF(G52=1,R52*(1-1.0),IF(H51=0,1,O51*(1+0.00023125256064071564))) | P52: =IF(G52=1,IF(H51=0,1,ABS(0.2-J51*B52/I52)+ABS(0.2-K51*C52/I52)+ABS(0.2-L51*D52/I52)+ABS(0.2-M51*E52/I52)+ABS(0.2-N51*F52/I52)),0) | Q52: =P52*0.0015 | R52: =I52*(1-Q52) | S52: =R52/R51-1 | T52: =MAX(T51,R52) | U52: =R52/T52-1 | V52: 1.095679 | W52: =R52-V52
A53: 38516 | B53: =Prices!B53 | C53: =Prices!C53 | D53: =Prices!D53 | E53: =Prices!E53 | F53: =Prices!F53 | G53: =IF(AND(51>=16,TEXT(A53,"yyyy-mm")<>TEXT(A54,"yyyy-mm")),1,0) | H53: =IF(OR(H52=1,G53=1),1,0) | I53: =IF(H52=0,1,SUMPRODUCT(J52:N52,B53:F53)+O52*(1+0.00023125256064071564)) | J53: =IF(G53=1,0.2*R53/B53,J52) | K53: =IF(G53=1,0.2*R53/C53,K52) | L53: =IF(G53=1,0.2*R53/D53,L52) | M53: =IF(G53=1,0.2*R53/E53,M52) | N53: =IF(G53=1,0.2*R53/F53,N52) | O53: =IF(G53=1,R53*(1-1.0),IF(H52=0,1,O52*(1+0.00023125256064071564))) | P53: =IF(G53=1,IF(H52=0,1,ABS(0.2-J52*B53/I53)+ABS(0.2-K52*C53/I53)+ABS(0.2-L52*D53/I53)+ABS(0.2-M52*E53/I53)+ABS(0.2-N52*F53/I53)),0) | Q53: =P53*0.0015 | R53: =I53*(1-Q53) | S53: =R53/R52-1 | T53: =MAX(T52,R53) | U53: =R53/T53-1 | V53: 1.0949744 | W53: =R53-V53
A54: 38517 | B54: =Prices!B54 | C54: =Prices!C54 | D54: =Prices!D54 | E54: =Prices!E54 | F54: =Prices!F54 | G54: =IF(AND(52>=16,TEXT(A54,"yyyy-mm")<>TEXT(A55,"yyyy-mm")),1,0) | H54: =IF(OR(H53=1,G54=1),1,0) | I54: =IF(H53=0,1,SUMPRODUCT(J53:N53,B54:F54)+O53*(1+0.00023125256064071564)) | J54: =IF(G54=1,0.2*R54/B54,J53) | K54: =IF(G54=1,0.2*R54/C54,K53) | L54: =IF(G54=1,0.2*R54/D54,L53) | M54: =IF(G54=1,0.2*R54/E54,M53) | N54: =IF(G54=1,0.2*R54/F54,N53) | O54: =IF(G54=1,R54*(1-1.0),IF(H53=0,1,O53*(1+0.00023125256064071564))) | P54: =IF(G54=1,IF(H53=0,1,ABS(0.2-J53*B54/I54)+ABS(0.2-K53*C54/I54)+ABS(0.2-L53*D54/I54)+ABS(0.2-M53*E54/I54)+ABS(0.2-N53*F54/I54)),0) | Q54: =P54*0.0015 | R54: =I54*(1-Q54) | S54: =R54/R53-1 | T54: =MAX(T53,R54) | U54: =R54/T54-1 | V54: 1.0985388 | W54: =R54-V54
A55: 38518 | B55: =Prices!B55 | C55: =Prices!C55 | D55: =Prices!D55 | E55: =Prices!E55 | F55: =Prices!F55 | G55: =IF(AND(53>=16,TEXT(A55,"yyyy-mm")<>TEXT(A56,"yyyy-mm")),1,0) | H55: =IF(OR(H54=1,G55=1),1,0) | I55: =IF(H54=0,1,SUMPRODUCT(J54:N54,B55:F55)+O54*(1+0.00023125256064071564)) | J55: =IF(G55=1,0.2*R55/B55,J54) | K55: =IF(G55=1,0.2*R55/C55,K54) | L55: =IF(G55=1,0.2*R55/D55,L54) | M55: =IF(G55=1,0.2*R55/E55,M54) | N55: =IF(G55=1,0.2*R55/F55,N54) | O55: =IF(G55=1,R55*(1-1.0),IF(H54=0,1,O54*(1+0.00023125256064071564))) | P55: =IF(G55=1,IF(H54=0,1,ABS(0.2-J54*B55/I55)+ABS(0.2-K54*C55/I55)+ABS(0.2-L54*D55/I55)+ABS(0.2-M54*E55/I55)+ABS(0.2-N54*F55/I55)),0) | Q55: =P55*0.0015 | R55: =I55*(1-Q55) | S55: =R55/R54-1 | T55: =MAX(T54,R55) | U55: =R55/T55-1 | V55: 1.1035061 | W55: =R55-V55
A56: 38519 | B56: =Prices!B56 | C56: =Prices!C56 | D56: =Prices!D56 | E56: =Prices!E56 | F56: =Prices!F56 | G56: =IF(AND(54>=16,TEXT(A56,"yyyy-mm")<>TEXT(A57,"yyyy-mm")),1,0) | H56: =IF(OR(H55=1,G56=1),1,0) | I56: =IF(H55=0,1,SUMPRODUCT(J55:N55,B56:F56)+O55*(1+0.00023125256064071564)) | J56: =IF(G56=1,0.2*R56/B56,J55) | K56: =IF(G56=1,0.2*R56/C56,K55) | L56: =IF(G56=1,0.2*R56/D56,L55) | M56: =IF(G56=1,0.2*R56/E56,M55) | N56: =IF(G56=1,0.2*R56/F56,N55) | O56: =IF(G56=1,R56*(1-1.0),IF(H55=0,1,O55*(1+0.00023125256064071564))) | P56: =IF(G56=1,IF(H55=0,1,ABS(0.2-J55*B56/I56)+ABS(0.2-K55*C56/I56)+ABS(0.2-L55*D56/I56)+ABS(0.2-M55*E56/I56)+ABS(0.2-N55*F56/I56)),0) | Q56: =P56*0.0015 | R56: =I56*(1-Q56) | S56: =R56/R55-1 | T56: =MAX(T55,R56) | U56: =R56/T56-1 | V56: 1.0899724 | W56: =R56-V56
A57: 38520 | B57: =Prices!B57 | C57: =Prices!C57 | D57: =Prices!D57 | E57: =Prices!E57 | F57: =Prices!F57 | G57: =IF(AND(55>=16,TEXT(A57,"yyyy-mm")<>TEXT(A58,"yyyy-mm")),1,0) | H57: =IF(OR(H56=1,G57=1),1,0) | I57: =IF(H56=0,1,SUMPRODUCT(J56:N56,B57:F57)+O56*(1+0.00023125256064071564)) | J57: =IF(G57=1,0.2*R57/B57,J56) | K57: =IF(G57=1,0.2*R57/C57,K56) | L57: =IF(G57=1,0.2*R57/D57,L56) | M57: =IF(G57=1,0.2*R57/E57,M56) | N57: =IF(G57=1,0.2*R57/F57,N56) | O57: =IF(G57=1,R57*(1-1.0),IF(H56=0,1,O56*(1+0.00023125256064071564))) | P57: =IF(G57=1,IF(H56=0,1,ABS(0.2-J56*B57/I57)+ABS(0.2-K56*C57/I57)+ABS(0.2-L56*D57/I57)+ABS(0.2-M56*E57/I57)+ABS(0.2-N56*F57/I57)),0) | Q57: =P57*0.0015 | R57: =I57*(1-Q57) | S57: =R57/R56-1 | T57: =MAX(T56,R57) | U57: =R57/T57-1 | V57: 1.0791873 | W57: =R57-V57
A58: 38523 | B58: =Prices!B58 | C58: =Prices!C58 | D58: =Prices!D58 | E58: =Prices!E58 | F58: =Prices!F58 | G58: =IF(AND(56>=16,TEXT(A58,"yyyy-mm")<>TEXT(A59,"yyyy-mm")),1,0) | H58: =IF(OR(H57=1,G58=1),1,0) | I58: =IF(H57=0,1,SUMPRODUCT(J57:N57,B58:F58)+O57*(1+0.00023125256064071564)) | J58: =IF(G58=1,0.2*R58/B58,J57) | K58: =IF(G58=1,0.2*R58/C58,K57) | L58: =IF(G58=1,0.2*R58/D58,L57) | M58: =IF(G58=1,0.2*R58/E58,M57) | N58: =IF(G58=1,0.2*R58/F58,N57) | O58: =IF(G58=1,R58*(1-1.0),IF(H57=0,1,O57*(1+0.00023125256064071564))) | P58: =IF(G58=1,IF(H57=0,1,ABS(0.2-J57*B58/I58)+ABS(0.2-K57*C58/I58)+ABS(0.2-L57*D58/I58)+ABS(0.2-M57*E58/I58)+ABS(0.2-N57*F58/I58)),0) | Q58: =P58*0.0015 | R58: =I58*(1-Q58) | S58: =R58/R57-1 | T58: =MAX(T57,R58) | U58: =R58/T58-1 | V58: 1.0748581 | W58: =R58-V58
A59: 38524 | B59: =Prices!B59 | C59: =Prices!C59 | D59: =Prices!D59 | E59: =Prices!E59 | F59: =Prices!F59 | G59: =IF(AND(57>=16,TEXT(A59,"yyyy-mm")<>TEXT(A60,"yyyy-mm")),1,0) | H59: =IF(OR(H58=1,G59=1),1,0) | I59: =IF(H58=0,1,SUMPRODUCT(J58:N58,B59:F59)+O58*(1+0.00023125256064071564)) | J59: =IF(G59=1,0.2*R59/B59,J58) | K59: =IF(G59=1,0.2*R59/C59,K58) | L59: =IF(G59=1,0.2*R59/D59,L58) | M59: =IF(G59=1,0.2*R59/E59,M58) | N59: =IF(G59=1,0.2*R59/F59,N58) | O59: =IF(G59=1,R59*(1-1.0),IF(H58=0,1,O58*(1+0.00023125256064071564))) | P59: =IF(G59=1,IF(H58=0,1,ABS(0.2-J58*B59/I59)+ABS(0.2-K58*C59/I59)+ABS(0.2-L58*D59/I59)+ABS(0.2-M58*E59/I59)+ABS(0.2-N58*F59/I59)),0) | Q59: =P59*0.0015 | R59: =I59*(1-Q59) | S59: =R59/R58-1 | T59: =MAX(T58,R59) | U59: =R59/T59-1 | V59: 1.0820641 | W59: =R59-V59
A60: 38525 | B60: =Prices!B60 | C60: =Prices!C60 | D60: =Prices!D60 | E60: =Prices!E60 | F60: =Prices!F60 | G60: =IF(AND(58>=16,TEXT(A60,"yyyy-mm")<>TEXT(A61,"yyyy-mm")),1,0) | H60: =IF(OR(H59=1,G60=1),1,0) | I60: =IF(H59=0,1,SUMPRODUCT(J59:N59,B60:F60)+O59*(1+0.00023125256064071564)) | J60: =IF(G60=1,0.2*R60/B60,J59) | K60: =IF(G60=1,0.2*R60/C60,K59) | L60: =IF(G60=1,0.2*R60/D60,L59) | M60: =IF(G60=1,0.2*R60/E60,M59) | N60: =IF(G60=1,0.2*R60/F60,N59) | O60: =IF(G60=1,R60*(1-1.0),IF(H59=0,1,O59*(1+0.00023125256064071564))) | P60: =IF(G60=1,IF(H59=0,1,ABS(0.2-J59*B60/I60)+ABS(0.2-K59*C60/I60)+ABS(0.2-L59*D60/I60)+ABS(0.2-M59*E60/I60)+ABS(0.2-N59*F60/I60)),0) | Q60: =P60*0.0015 | R60: =I60*(1-Q60) | S60: =R60/R59-1 | T60: =MAX(T59,R60) | U60: =R60/T60-1 | V60: 1.0851392 | W60: =R60-V60
A61: 38526 | B61: =Prices!B61 | C61: =Prices!C61 | D61: =Prices!D61 | E61: =Prices!E61 | F61: =Prices!F61 | G61: =IF(AND(59>=16,TEXT(A61,"yyyy-mm")<>TEXT(A62,"yyyy-mm")),1,0) | H61: =IF(OR(H60=1,G61=1),1,0) | I61: =IF(H60=0,1,SUMPRODUCT(J60:N60,B61:F61)+O60*(1+0.00023125256064071564)) | J61: =IF(G61=1,0.2*R61/B61,J60) | K61: =IF(G61=1,0.2*R61/C61,K60) | L61: =IF(G61=1,0.2*R61/D61,L60) | M61: =IF(G61=1,0.2*R61/E61,M60) | N61: =IF(G61=1,0.2*R61/F61,N60) | O61: =IF(G61=1,R61*(1-1.0),IF(H60=0,1,O60*(1+0.00023125256064071564))) | P61: =IF(G61=1,IF(H60=0,1,ABS(0.2-J60*B61/I61)+ABS(0.2-K60*C61/I61)+ABS(0.2-L60*D61/I61)+ABS(0.2-M60*E61/I61)+ABS(0.2-N60*F61/I61)),0) | Q61: =P61*0.0015 | R61: =I61*(1-Q61) | S61: =R61/R60-1 | T61: =MAX(T60,R61) | U61: =R61/T61-1 | V61: 1.0891077 | W61: =R61-V61
A62: 38527 | B62: =Prices!B62 | C62: =Prices!C62 | D62: =Prices!D62 | E62: =Prices!E62 | F62: =Prices!F62 | G62: =IF(AND(60>=16,TEXT(A62,"yyyy-mm")<>TEXT(A63,"yyyy-mm")),1,0) | H62: =IF(OR(H61=1,G62=1),1,0) | I62: =IF(H61=0,1,SUMPRODUCT(J61:N61,B62:F62)+O61*(1+0.00023125256064071564)) | J62: =IF(G62=1,0.2*R62/B62,J61) | K62: =IF(G62=1,0.2*R62/C62,K61) | L62: =IF(G62=1,0.2*R62/D62,L61) | M62: =IF(G62=1,0.2*R62/E62,M61) | N62: =IF(G62=1,0.2*R62/F62,N61) | O62: =IF(G62=1,R62*(1-1.0),IF(H61=0,1,O61*(1+0.00023125256064071564))) | P62: =IF(G62=1,IF(H61=0,1,ABS(0.2-J61*B62/I62)+ABS(0.2-K61*C62/I62)+ABS(0.2-L61*D62/I62)+ABS(0.2-M61*E62/I62)+ABS(0.2-N61*F62/I62)),0) | Q62: =P62*0.0015 | R62: =I62*(1-Q62) | S62: =R62/R61-1 | T62: =MAX(T61,R62) | U62: =R62/T62-1 | V62: 1.0969486 | W62: =R62-V62
A63: 38530 | B63: =Prices!B63 | C63: =Prices!C63 | D63: =Prices!D63 | E63: =Prices!E63 | F63: =Prices!F63 | G63: =IF(AND(61>=16,TEXT(A63,"yyyy-mm")<>TEXT(A64,"yyyy-mm")),1,0) | H63: =IF(OR(H62=1,G63=1),1,0) | I63: =IF(H62=0,1,SUMPRODUCT(J62:N62,B63:F63)+O62*(1+0.00023125256064071564)) | J63: =IF(G63=1,0.2*R63/B63,J62) | K63: =IF(G63=1,0.2*R63/C63,K62) | L63: =IF(G63=1,0.2*R63/D63,L62) | M63: =IF(G63=1,0.2*R63/E63,M62) | N63: =IF(G63=1,0.2*R63/F63,N62) | O63: =IF(G63=1,R63*(1-1.0),IF(H62=0,1,O62*(1+0.00023125256064071564))) | P63: =IF(G63=1,IF(H62=0,1,ABS(0.2-J62*B63/I63)+ABS(0.2-K62*C63/I63)+ABS(0.2-L62*D63/I63)+ABS(0.2-M62*E63/I63)+ABS(0.2-N62*F63/I63)),0) | Q63: =P63*0.0015 | R63: =I63*(1-Q63) | S63: =R63/R62-1 | T63: =MAX(T62,R63) | U63: =R63/T63-1 | V63: 1.0961135 | W63: =R63-V63
A64: 38531 | B64: =Prices!B64 | C64: =Prices!C64 | D64: =Prices!D64 | E64: =Prices!E64 | F64: =Prices!F64 | G64: =IF(AND(62>=16,TEXT(A64,"yyyy-mm")<>TEXT(A65,"yyyy-mm")),1,0) | H64: =IF(OR(H63=1,G64=1),1,0) | I64: =IF(H63=0,1,SUMPRODUCT(J63:N63,B64:F64)+O63*(1+0.00023125256064071564)) | J64: =IF(G64=1,0.2*R64/B64,J63) | K64: =IF(G64=1,0.2*R64/C64,K63) | L64: =IF(G64=1,0.2*R64/D64,L63) | M64: =IF(G64=1,0.2*R64/E64,M63) | N64: =IF(G64=1,0.2*R64/F64,N63) | O64: =IF(G64=1,R64*(1-1.0),IF(H63=0,1,O63*(1+0.00023125256064071564))) | P64: =IF(G64=1,IF(H63=0,1,ABS(0.2-J63*B64/I64)+ABS(0.2-K63*C64/I64)+ABS(0.2-L63*D64/I64)+ABS(0.2-M63*E64/I64)+ABS(0.2-N63*F64/I64)),0) | Q64: =P64*0.0015 | R64: =I64*(1-Q64) | S64: =R64/R63-1 | T64: =MAX(T63,R64) | U64: =R64/T64-1 | V64: 1.0774574 | W64: =R64-V64
A65: 38532 | B65: =Prices!B65 | C65: =Prices!C65 | D65: =Prices!D65 | E65: =Prices!E65 | F65: =Prices!F65 | G65: =IF(AND(63>=16,TEXT(A65,"yyyy-mm")<>TEXT(A66,"yyyy-mm")),1,0) | H65: =IF(OR(H64=1,G65=1),1,0) | I65: =IF(H64=0,1,SUMPRODUCT(J64:N64,B65:F65)+O64*(1+0.00023125256064071564)) | J65: =IF(G65=1,0.2*R65/B65,J64) | K65: =IF(G65=1,0.2*R65/C65,K64) | L65: =IF(G65=1,0.2*R65/D65,L64) | M65: =IF(G65=1,0.2*R65/E65,M64) | N65: =IF(G65=1,0.2*R65/F65,N64) | O65: =IF(G65=1,R65*(1-1.0),IF(H64=0,1,O64*(1+0.00023125256064071564))) | P65: =IF(G65=1,IF(H64=0,1,ABS(0.2-J64*B65/I65)+ABS(0.2-K64*C65/I65)+ABS(0.2-L64*D65/I65)+ABS(0.2-M64*E65/I65)+ABS(0.2-N64*F65/I65)),0) | Q65: =P65*0.0015 | R65: =I65*(1-Q65) | S65: =R65/R64-1 | T65: =MAX(T64,R65) | U65: =R65/T65-1 | V65: 1.0876533 | W65: =R65-V65
A66: 38533 | B66: =Prices!B66 | C66: =Prices!C66 | D66: =Prices!D66 | E66: =Prices!E66 | F66: =Prices!F66 | G66: =IF(AND(64>=16,TEXT(A66,"yyyy-mm")<>TEXT(A67,"yyyy-mm")),1,0) | H66: =IF(OR(H65=1,G66=1),1,0) | I66: =IF(H65=0,1,SUMPRODUCT(J65:N65,B66:F66)+O65*(1+0.00023125256064071564)) | J66: =IF(G66=1,0.2*R66/B66,J65) | K66: =IF(G66=1,0.2*R66/C66,K65) | L66: =IF(G66=1,0.2*R66/D66,L65) | M66: =IF(G66=1,0.2*R66/E66,M65) | N66: =IF(G66=1,0.2*R66/F66,N65) | O66: =IF(G66=1,R66*(1-1.0),IF(H65=0,1,O65*(1+0.00023125256064071564))) | P66: =IF(G66=1,IF(H65=0,1,ABS(0.2-J65*B66/I66)+ABS(0.2-K65*C66/I66)+ABS(0.2-L65*D66/I66)+ABS(0.2-M65*E66/I66)+ABS(0.2-N65*F66/I66)),0) | Q66: =P66*0.0015 | R66: =I66*(1-Q66) | S66: =R66/R65-1 | T66: =MAX(T65,R66) | U66: =R66/T66-1 | V66: 1.0902052 | W66: =R66-V66
A67: 38534 | B67: =Prices!B67 | C67: =Prices!C67 | D67: =Prices!D67 | E67: =Prices!E67 | F67: =Prices!F67 | G67: =IF(AND(65>=16,TEXT(A67,"yyyy-mm")<>TEXT(A68,"yyyy-mm")),1,0) | H67: =IF(OR(H66=1,G67=1),1,0) | I67: =IF(H66=0,1,SUMPRODUCT(J66:N66,B67:F67)+O66*(1+0.00023125256064071564)) | J67: =IF(G67=1,0.2*R67/B67,J66) | K67: =IF(G67=1,0.2*R67/C67,K66) | L67: =IF(G67=1,0.2*R67/D67,L66) | M67: =IF(G67=1,0.2*R67/E67,M66) | N67: =IF(G67=1,0.2*R67/F67,N66) | O67: =IF(G67=1,R67*(1-1.0),IF(H66=0,1,O66*(1+0.00023125256064071564))) | P67: =IF(G67=1,IF(H66=0,1,ABS(0.2-J66*B67/I67)+ABS(0.2-K66*C67/I67)+ABS(0.2-L66*D67/I67)+ABS(0.2-M66*E67/I67)+ABS(0.2-N66*F67/I67)),0) | Q67: =P67*0.0015 | R67: =I67*(1-Q67) | S67: =R67/R66-1 | T67: =MAX(T66,R67) | U67: =R67/T67-1 | V67: 1.1030447 | W67: =R67-V67
A68: 38537 | B68: =Prices!B68 | C68: =Prices!C68 | D68: =Prices!D68 | E68: =Prices!E68 | F68: =Prices!F68 | G68: =IF(AND(66>=16,TEXT(A68,"yyyy-mm")<>TEXT(A69,"yyyy-mm")),1,0) | H68: =IF(OR(H67=1,G68=1),1,0) | I68: =IF(H67=0,1,SUMPRODUCT(J67:N67,B68:F68)+O67*(1+0.00023125256064071564)) | J68: =IF(G68=1,0.2*R68/B68,J67) | K68: =IF(G68=1,0.2*R68/C68,K67) | L68: =IF(G68=1,0.2*R68/D68,L67) | M68: =IF(G68=1,0.2*R68/E68,M67) | N68: =IF(G68=1,0.2*R68/F68,N67) | O68: =IF(G68=1,R68*(1-1.0),IF(H67=0,1,O67*(1+0.00023125256064071564))) | P68: =IF(G68=1,IF(H67=0,1,ABS(0.2-J67*B68/I68)+ABS(0.2-K67*C68/I68)+ABS(0.2-L67*D68/I68)+ABS(0.2-M67*E68/I68)+ABS(0.2-N67*F68/I68)),0) | Q68: =P68*0.0015 | R68: =I68*(1-Q68) | S68: =R68/R67-1 | T68: =MAX(T67,R68) | U68: =R68/T68-1 | V68: 1.1178724 | W68: =R68-V68
A69: 38538 | B69: =Prices!B69 | C69: =Prices!C69 | D69: =Prices!D69 | E69: =Prices!E69 | F69: =Prices!F69 | G69: =IF(AND(67>=16,TEXT(A69,"yyyy-mm")<>TEXT(A70,"yyyy-mm")),1,0) | H69: =IF(OR(H68=1,G69=1),1,0) | I69: =IF(H68=0,1,SUMPRODUCT(J68:N68,B69:F69)+O68*(1+0.00023125256064071564)) | J69: =IF(G69=1,0.2*R69/B69,J68) | K69: =IF(G69=1,0.2*R69/C69,K68) | L69: =IF(G69=1,0.2*R69/D69,L68) | M69: =IF(G69=1,0.2*R69/E69,M68) | N69: =IF(G69=1,0.2*R69/F69,N68) | O69: =IF(G69=1,R69*(1-1.0),IF(H68=0,1,O68*(1+0.00023125256064071564))) | P69: =IF(G69=1,IF(H68=0,1,ABS(0.2-J68*B69/I69)+ABS(0.2-K68*C69/I69)+ABS(0.2-L68*D69/I69)+ABS(0.2-M68*E69/I69)+ABS(0.2-N68*F69/I69)),0) | Q69: =P69*0.0015 | R69: =I69*(1-Q69) | S69: =R69/R68-1 | T69: =MAX(T68,R69) | U69: =R69/T69-1 | V69: 1.1108504 | W69: =R69-V69
A70: 38539 | B70: =Prices!B70 | C70: =Prices!C70 | D70: =Prices!D70 | E70: =Prices!E70 | F70: =Prices!F70 | G70: =IF(AND(68>=16,TEXT(A70,"yyyy-mm")<>TEXT(A71,"yyyy-mm")),1,0) | H70: =IF(OR(H69=1,G70=1),1,0) | I70: =IF(H69=0,1,SUMPRODUCT(J69:N69,B70:F70)+O69*(1+0.00023125256064071564)) | J70: =IF(G70=1,0.2*R70/B70,J69) | K70: =IF(G70=1,0.2*R70/C70,K69) | L70: =IF(G70=1,0.2*R70/D70,L69) | M70: =IF(G70=1,0.2*R70/E70,M69) | N70: =IF(G70=1,0.2*R70/F70,N69) | O70: =IF(G70=1,R70*(1-1.0),IF(H69=0,1,O69*(1+0.00023125256064071564))) | P70: =IF(G70=1,IF(H69=0,1,ABS(0.2-J69*B70/I70)+ABS(0.2-K69*C70/I70)+ABS(0.2-L69*D70/I70)+ABS(0.2-M69*E70/I70)+ABS(0.2-N69*F70/I70)),0) | Q70: =P70*0.0015 | R70: =I70*(1-Q70) | S70: =R70/R69-1 | T70: =MAX(T69,R70) | U70: =R70/T70-1 | V70: 1.1278507 | W70: =R70-V70
A71: 38540 | B71: =Prices!B71 | C71: =Prices!C71 | D71: =Prices!D71 | E71: =Prices!E71 | F71: =Prices!F71 | G71: =IF(AND(69>=16,TEXT(A71,"yyyy-mm")<>TEXT(A72,"yyyy-mm")),1,0) | H71: =IF(OR(H70=1,G71=1),1,0) | I71: =IF(H70=0,1,SUMPRODUCT(J70:N70,B71:F71)+O70*(1+0.00023125256064071564)) | J71: =IF(G71=1,0.2*R71/B71,J70) | K71: =IF(G71=1,0.2*R71/C71,K70) | L71: =IF(G71=1,0.2*R71/D71,L70) | M71: =IF(G71=1,0.2*R71/E71,M70) | N71: =IF(G71=1,0.2*R71/F71,N70) | O71: =IF(G71=1,R71*(1-1.0),IF(H70=0,1,O70*(1+0.00023125256064071564))) | P71: =IF(G71=1,IF(H70=0,1,ABS(0.2-J70*B71/I71)+ABS(0.2-K70*C71/I71)+ABS(0.2-L70*D71/I71)+ABS(0.2-M70*E71/I71)+ABS(0.2-N70*F71/I71)),0) | Q71: =P71*0.0015 | R71: =I71*(1-Q71) | S71: =R71/R70-1 | T71: =MAX(T70,R71) | U71: =R71/T71-1 | V71: 1.1113904 | W71: =R71-V71
A72: 38541 | B72: =Prices!B72 | C72: =Prices!C72 | D72: =Prices!D72 | E72: =Prices!E72 | F72: =Prices!F72 | G72: =IF(AND(70>=16,TEXT(A72,"yyyy-mm")<>TEXT(A73,"yyyy-mm")),1,0) | H72: =IF(OR(H71=1,G72=1),1,0) | I72: =IF(H71=0,1,SUMPRODUCT(J71:N71,B72:F72)+O71*(1+0.00023125256064071564)) | J72: =IF(G72=1,0.2*R72/B72,J71) | K72: =IF(G72=1,0.2*R72/C72,K71) | L72: =IF(G72=1,0.2*R72/D72,L71) | M72: =IF(G72=1,0.2*R72/E72,M71) | N72: =IF(G72=1,0.2*R72/F72,N71) | O72: =IF(G72=1,R72*(1-1.0),IF(H71=0,1,O71*(1+0.00023125256064071564))) | P72: =IF(G72=1,IF(H71=0,1,ABS(0.2-J71*B72/I72)+ABS(0.2-K71*C72/I72)+ABS(0.2-L71*D72/I72)+ABS(0.2-M71*E72/I72)+ABS(0.2-N71*F72/I72)),0) | Q72: =P72*0.0015 | R72: =I72*(1-Q72) | S72: =R72/R71-1 | T72: =MAX(T71,R72) | U72: =R72/T72-1 | V72: 1.1292299 | W72: =R72-V72
A73: 38544 | B73: =Prices!B73 | C73: =Prices!C73 | D73: =Prices!D73 | E73: =Prices!E73 | F73: =Prices!F73 | G73: =IF(AND(71>=16,TEXT(A73,"yyyy-mm")<>TEXT(A74,"yyyy-mm")),1,0) | H73: =IF(OR(H72=1,G73=1),1,0) | I73: =IF(H72=0,1,SUMPRODUCT(J72:N72,B73:F73)+O72*(1+0.00023125256064071564)) | J73: =IF(G73=1,0.2*R73/B73,J72) | K73: =IF(G73=1,0.2*R73/C73,K72) | L73: =IF(G73=1,0.2*R73/D73,L72) | M73: =IF(G73=1,0.2*R73/E73,M72) | N73: =IF(G73=1,0.2*R73/F73,N72) | O73: =IF(G73=1,R73*(1-1.0),IF(H72=0,1,O72*(1+0.00023125256064071564))) | P73: =IF(G73=1,IF(H72=0,1,ABS(0.2-J72*B73/I73)+ABS(0.2-K72*C73/I73)+ABS(0.2-L72*D73/I73)+ABS(0.2-M72*E73/I73)+ABS(0.2-N72*F73/I73)),0) | Q73: =P73*0.0015 | R73: =I73*(1-Q73) | S73: =R73/R72-1 | T73: =MAX(T72,R73) | U73: =R73/T73-1 | V73: 1.1468785 | W73: =R73-V73
A74: 38545 | B74: =Prices!B74 | C74: =Prices!C74 | D74: =Prices!D74 | E74: =Prices!E74 | F74: =Prices!F74 | G74: =IF(AND(72>=16,TEXT(A74,"yyyy-mm")<>TEXT(A75,"yyyy-mm")),1,0) | H74: =IF(OR(H73=1,G74=1),1,0) | I74: =IF(H73=0,1,SUMPRODUCT(J73:N73,B74:F74)+O73*(1+0.00023125256064071564)) | J74: =IF(G74=1,0.2*R74/B74,J73) | K74: =IF(G74=1,0.2*R74/C74,K73) | L74: =IF(G74=1,0.2*R74/D74,L73) | M74: =IF(G74=1,0.2*R74/E74,M73) | N74: =IF(G74=1,0.2*R74/F74,N73) | O74: =IF(G74=1,R74*(1-1.0),IF(H73=0,1,O73*(1+0.00023125256064071564))) | P74: =IF(G74=1,IF(H73=0,1,ABS(0.2-J73*B74/I74)+ABS(0.2-K73*C74/I74)+ABS(0.2-L73*D74/I74)+ABS(0.2-M73*E74/I74)+ABS(0.2-N73*F74/I74)),0) | Q74: =P74*0.0015 | R74: =I74*(1-Q74) | S74: =R74/R73-1 | T74: =MAX(T73,R74) | U74: =R74/T74-1 | V74: 1.150097 | W74: =R74-V74
A75: 38546 | B75: =Prices!B75 | C75: =Prices!C75 | D75: =Prices!D75 | E75: =Prices!E75 | F75: =Prices!F75 | G75: =IF(AND(73>=16,TEXT(A75,"yyyy-mm")<>TEXT(A76,"yyyy-mm")),1,0) | H75: =IF(OR(H74=1,G75=1),1,0) | I75: =IF(H74=0,1,SUMPRODUCT(J74:N74,B75:F75)+O74*(1+0.00023125256064071564)) | J75: =IF(G75=1,0.2*R75/B75,J74) | K75: =IF(G75=1,0.2*R75/C75,K74) | L75: =IF(G75=1,0.2*R75/D75,L74) | M75: =IF(G75=1,0.2*R75/E75,M74) | N75: =IF(G75=1,0.2*R75/F75,N74) | O75: =IF(G75=1,R75*(1-1.0),IF(H74=0,1,O74*(1+0.00023125256064071564))) | P75: =IF(G75=1,IF(H74=0,1,ABS(0.2-J74*B75/I75)+ABS(0.2-K74*C75/I75)+ABS(0.2-L74*D75/I75)+ABS(0.2-M74*E75/I75)+ABS(0.2-N74*F75/I75)),0) | Q75: =P75*0.0015 | R75: =I75*(1-Q75) | S75: =R75/R74-1 | T75: =MAX(T74,R75) | U75: =R75/T75-1 | V75: 1.153198 | W75: =R75-V75
A76: 38547 | B76: =Prices!B76 | C76: =Prices!C76 | D76: =Prices!D76 | E76: =Prices!E76 | F76: =Prices!F76 | G76: =IF(AND(74>=16,TEXT(A76,"yyyy-mm")<>TEXT(A77,"yyyy-mm")),1,0) | H76: =IF(OR(H75=1,G76=1),1,0) | I76: =IF(H75=0,1,SUMPRODUCT(J75:N75,B76:F76)+O75*(1+0.00023125256064071564)) | J76: =IF(G76=1,0.2*R76/B76,J75) | K76: =IF(G76=1,0.2*R76/C76,K75) | L76: =IF(G76=1,0.2*R76/D76,L75) | M76: =IF(G76=1,0.2*R76/E76,M75) | N76: =IF(G76=1,0.2*R76/F76,N75) | O76: =IF(G76=1,R76*(1-1.0),IF(H75=0,1,O75*(1+0.00023125256064071564))) | P76: =IF(G76=1,IF(H75=0,1,ABS(0.2-J75*B76/I76)+ABS(0.2-K75*C76/I76)+ABS(0.2-L75*D76/I76)+ABS(0.2-M75*E76/I76)+ABS(0.2-N75*F76/I76)),0) | Q76: =P76*0.0015 | R76: =I76*(1-Q76) | S76: =R76/R75-1 | T76: =MAX(T75,R76) | U76: =R76/T76-1 | V76: 1.1511195 | W76: =R76-V76
A77: 38548 | B77: =Prices!B77 | C77: =Prices!C77 | D77: =Prices!D77 | E77: =Prices!E77 | F77: =Prices!F77 | G77: =IF(AND(75>=16,TEXT(A77,"yyyy-mm")<>TEXT(A78,"yyyy-mm")),1,0) | H77: =IF(OR(H76=1,G77=1),1,0) | I77: =IF(H76=0,1,SUMPRODUCT(J76:N76,B77:F77)+O76*(1+0.00023125256064071564)) | J77: =IF(G77=1,0.2*R77/B77,J76) | K77: =IF(G77=1,0.2*R77/C77,K76) | L77: =IF(G77=1,0.2*R77/D77,L76) | M77: =IF(G77=1,0.2*R77/E77,M76) | N77: =IF(G77=1,0.2*R77/F77,N76) | O77: =IF(G77=1,R77*(1-1.0),IF(H76=0,1,O76*(1+0.00023125256064071564))) | P77: =IF(G77=1,IF(H76=0,1,ABS(0.2-J76*B77/I77)+ABS(0.2-K76*C77/I77)+ABS(0.2-L76*D77/I77)+ABS(0.2-M76*E77/I77)+ABS(0.2-N76*F77/I77)),0) | Q77: =P77*0.0015 | R77: =I77*(1-Q77) | S77: =R77/R76-1 | T77: =MAX(T76,R77) | U77: =R77/T77-1 | V77: 1.1633067 | W77: =R77-V77
A78: 38551 | B78: =Prices!B78 | C78: =Prices!C78 | D78: =Prices!D78 | E78: =Prices!E78 | F78: =Prices!F78 | G78: =IF(AND(76>=16,TEXT(A78,"yyyy-mm")<>TEXT(A79,"yyyy-mm")),1,0) | H78: =IF(OR(H77=1,G78=1),1,0) | I78: =IF(H77=0,1,SUMPRODUCT(J77:N77,B78:F78)+O77*(1+0.00023125256064071564)) | J78: =IF(G78=1,0.2*R78/B78,J77) | K78: =IF(G78=1,0.2*R78/C78,K77) | L78: =IF(G78=1,0.2*R78/D78,L77) | M78: =IF(G78=1,0.2*R78/E78,M77) | N78: =IF(G78=1,0.2*R78/F78,N77) | O78: =IF(G78=1,R78*(1-1.0),IF(H77=0,1,O77*(1+0.00023125256064071564))) | P78: =IF(G78=1,IF(H77=0,1,ABS(0.2-J77*B78/I78)+ABS(0.2-K77*C78/I78)+ABS(0.2-L77*D78/I78)+ABS(0.2-M77*E78/I78)+ABS(0.2-N77*F78/I78)),0) | Q78: =P78*0.0015 | R78: =I78*(1-Q78) | S78: =R78/R77-1 | T78: =MAX(T77,R78) | U78: =R78/T78-1 | V78: 1.1826508 | W78: =R78-V78
A79: 38552 | B79: =Prices!B79 | C79: =Prices!C79 | D79: =Prices!D79 | E79: =Prices!E79 | F79: =Prices!F79 | G79: =IF(AND(77>=16,TEXT(A79,"yyyy-mm")<>TEXT(A80,"yyyy-mm")),1,0) | H79: =IF(OR(H78=1,G79=1),1,0) | I79: =IF(H78=0,1,SUMPRODUCT(J78:N78,B79:F79)+O78*(1+0.00023125256064071564)) | J79: =IF(G79=1,0.2*R79/B79,J78) | K79: =IF(G79=1,0.2*R79/C79,K78) | L79: =IF(G79=1,0.2*R79/D79,L78) | M79: =IF(G79=1,0.2*R79/E79,M78) | N79: =IF(G79=1,0.2*R79/F79,N78) | O79: =IF(G79=1,R79*(1-1.0),IF(H78=0,1,O78*(1+0.00023125256064071564))) | P79: =IF(G79=1,IF(H78=0,1,ABS(0.2-J78*B79/I79)+ABS(0.2-K78*C79/I79)+ABS(0.2-L78*D79/I79)+ABS(0.2-M78*E79/I79)+ABS(0.2-N78*F79/I79)),0) | Q79: =P79*0.0015 | R79: =I79*(1-Q79) | S79: =R79/R78-1 | T79: =MAX(T78,R79) | U79: =R79/T79-1 | V79: 1.1870765 | W79: =R79-V79
A80: 38553 | B80: =Prices!B80 | C80: =Prices!C80 | D80: =Prices!D80 | E80: =Prices!E80 | F80: =Prices!F80 | G80: =IF(AND(78>=16,TEXT(A80,"yyyy-mm")<>TEXT(A81,"yyyy-mm")),1,0) | H80: =IF(OR(H79=1,G80=1),1,0) | I80: =IF(H79=0,1,SUMPRODUCT(J79:N79,B80:F80)+O79*(1+0.00023125256064071564)) | J80: =IF(G80=1,0.2*R80/B80,J79) | K80: =IF(G80=1,0.2*R80/C80,K79) | L80: =IF(G80=1,0.2*R80/D80,L79) | M80: =IF(G80=1,0.2*R80/E80,M79) | N80: =IF(G80=1,0.2*R80/F80,N79) | O80: =IF(G80=1,R80*(1-1.0),IF(H79=0,1,O79*(1+0.00023125256064071564))) | P80: =IF(G80=1,IF(H79=0,1,ABS(0.2-J79*B80/I80)+ABS(0.2-K79*C80/I80)+ABS(0.2-L79*D80/I80)+ABS(0.2-M79*E80/I80)+ABS(0.2-N79*F80/I80)),0) | Q80: =P80*0.0015 | R80: =I80*(1-Q80) | S80: =R80/R79-1 | T80: =MAX(T79,R80) | U80: =R80/T80-1 | V80: 1.1895857 | W80: =R80-V80
A81: 38554 | B81: =Prices!B81 | C81: =Prices!C81 | D81: =Prices!D81 | E81: =Prices!E81 | F81: =Prices!F81 | G81: =IF(AND(79>=16,TEXT(A81,"yyyy-mm")<>TEXT(A82,"yyyy-mm")),1,0) | H81: =IF(OR(H80=1,G81=1),1,0) | I81: =IF(H80=0,1,SUMPRODUCT(J80:N80,B81:F81)+O80*(1+0.00023125256064071564)) | J81: =IF(G81=1,0.2*R81/B81,J80) | K81: =IF(G81=1,0.2*R81/C81,K80) | L81: =IF(G81=1,0.2*R81/D81,L80) | M81: =IF(G81=1,0.2*R81/E81,M80) | N81: =IF(G81=1,0.2*R81/F81,N80) | O81: =IF(G81=1,R81*(1-1.0),IF(H80=0,1,O80*(1+0.00023125256064071564))) | P81: =IF(G81=1,IF(H80=0,1,ABS(0.2-J80*B81/I81)+ABS(0.2-K80*C81/I81)+ABS(0.2-L80*D81/I81)+ABS(0.2-M80*E81/I81)+ABS(0.2-N80*F81/I81)),0) | Q81: =P81*0.0015 | R81: =I81*(1-Q81) | S81: =R81/R80-1 | T81: =MAX(T80,R81) | U81: =R81/T81-1 | V81: 1.1865535 | W81: =R81-V81
A82: 38555 | B82: =Prices!B82 | C82: =Prices!C82 | D82: =Prices!D82 | E82: =Prices!E82 | F82: =Prices!F82 | G82: =IF(AND(80>=16,TEXT(A82,"yyyy-mm")<>TEXT(A83,"yyyy-mm")),1,0) | H82: =IF(OR(H81=1,G82=1),1,0) | I82: =IF(H81=0,1,SUMPRODUCT(J81:N81,B82:F82)+O81*(1+0.00023125256064071564)) | J82: =IF(G82=1,0.2*R82/B82,J81) | K82: =IF(G82=1,0.2*R82/C82,K81) | L82: =IF(G82=1,0.2*R82/D82,L81) | M82: =IF(G82=1,0.2*R82/E82,M81) | N82: =IF(G82=1,0.2*R82/F82,N81) | O82: =IF(G82=1,R82*(1-1.0),IF(H81=0,1,O81*(1+0.00023125256064071564))) | P82: =IF(G82=1,IF(H81=0,1,ABS(0.2-J81*B82/I82)+ABS(0.2-K81*C82/I82)+ABS(0.2-L81*D82/I82)+ABS(0.2-M81*E82/I82)+ABS(0.2-N81*F82/I82)),0) | Q82: =P82*0.0015 | R82: =I82*(1-Q82) | S82: =R82/R81-1 | T82: =MAX(T81,R82) | U82: =R82/T82-1 | V82: 1.2022831 | W82: =R82-V82
A83: 38558 | B83: =Prices!B83 | C83: =Prices!C83 | D83: =Prices!D83 | E83: =Prices!E83 | F83: =Prices!F83 | G83: =IF(AND(81>=16,TEXT(A83,"yyyy-mm")<>TEXT(A84,"yyyy-mm")),1,0) | H83: =IF(OR(H82=1,G83=1),1,0) | I83: =IF(H82=0,1,SUMPRODUCT(J82:N82,B83:F83)+O82*(1+0.00023125256064071564)) | J83: =IF(G83=1,0.2*R83/B83,J82) | K83: =IF(G83=1,0.2*R83/C83,K82) | L83: =IF(G83=1,0.2*R83/D83,L82) | M83: =IF(G83=1,0.2*R83/E83,M82) | N83: =IF(G83=1,0.2*R83/F83,N82) | O83: =IF(G83=1,R83*(1-1.0),IF(H82=0,1,O82*(1+0.00023125256064071564))) | P83: =IF(G83=1,IF(H82=0,1,ABS(0.2-J82*B83/I83)+ABS(0.2-K82*C83/I83)+ABS(0.2-L82*D83/I83)+ABS(0.2-M82*E83/I83)+ABS(0.2-N82*F83/I83)),0) | Q83: =P83*0.0015 | R83: =I83*(1-Q83) | S83: =R83/R82-1 | T83: =MAX(T82,R83) | U83: =R83/T83-1 | V83: 1.2073569 | W83: =R83-V83
A84: 38559 | B84: =Prices!B84 | C84: =Prices!C84 | D84: =Prices!D84 | E84: =Prices!E84 | F84: =Prices!F84 | G84: =IF(AND(82>=16,TEXT(A84,"yyyy-mm")<>TEXT(A85,"yyyy-mm")),1,0) | H84: =IF(OR(H83=1,G84=1),1,0) | I84: =IF(H83=0,1,SUMPRODUCT(J83:N83,B84:F84)+O83*(1+0.00023125256064071564)) | J84: =IF(G84=1,0.2*R84/B84,J83) | K84: =IF(G84=1,0.2*R84/C84,K83) | L84: =IF(G84=1,0.2*R84/D84,L83) | M84: =IF(G84=1,0.2*R84/E84,M83) | N84: =IF(G84=1,0.2*R84/F84,N83) | O84: =IF(G84=1,R84*(1-1.0),IF(H83=0,1,O83*(1+0.00023125256064071564))) | P84: =IF(G84=1,IF(H83=0,1,ABS(0.2-J83*B84/I84)+ABS(0.2-K83*C84/I84)+ABS(0.2-L83*D84/I84)+ABS(0.2-M83*E84/I84)+ABS(0.2-N83*F84/I84)),0) | Q84: =P84*0.0015 | R84: =I84*(1-Q84) | S84: =R84/R83-1 | T84: =MAX(T83,R84) | U84: =R84/T84-1 | V84: 1.2066447 | W84: =R84-V84
A85: 38560 | B85: =Prices!B85 | C85: =Prices!C85 | D85: =Prices!D85 | E85: =Prices!E85 | F85: =Prices!F85 | G85: =IF(AND(83>=16,TEXT(A85,"yyyy-mm")<>TEXT(A86,"yyyy-mm")),1,0) | H85: =IF(OR(H84=1,G85=1),1,0) | I85: =IF(H84=0,1,SUMPRODUCT(J84:N84,B85:F85)+O84*(1+0.00023125256064071564)) | J85: =IF(G85=1,0.2*R85/B85,J84) | K85: =IF(G85=1,0.2*R85/C85,K84) | L85: =IF(G85=1,0.2*R85/D85,L84) | M85: =IF(G85=1,0.2*R85/E85,M84) | N85: =IF(G85=1,0.2*R85/F85,N84) | O85: =IF(G85=1,R85*(1-1.0),IF(H84=0,1,O84*(1+0.00023125256064071564))) | P85: =IF(G85=1,IF(H84=0,1,ABS(0.2-J84*B85/I85)+ABS(0.2-K84*C85/I85)+ABS(0.2-L84*D85/I85)+ABS(0.2-M84*E85/I85)+ABS(0.2-N84*F85/I85)),0) | Q85: =P85*0.0015 | R85: =I85*(1-Q85) | S85: =R85/R84-1 | T85: =MAX(T84,R85) | U85: =R85/T85-1 | V85: 1.2087613 | W85: =R85-V85
A86: 38562 | B86: =Prices!B86 | C86: =Prices!C86 | D86: =Prices!D86 | E86: =Prices!E86 | F86: =Prices!F86 | G86: =IF(AND(84>=16,TEXT(A86,"yyyy-mm")<>TEXT(A87,"yyyy-mm")),1,0) | H86: =IF(OR(H85=1,G86=1),1,0) | I86: =IF(H85=0,1,SUMPRODUCT(J85:N85,B86:F86)+O85*(1+0.00023125256064071564)) | J86: =IF(G86=1,0.2*R86/B86,J85) | K86: =IF(G86=1,0.2*R86/C86,K85) | L86: =IF(G86=1,0.2*R86/D86,L85) | M86: =IF(G86=1,0.2*R86/E86,M85) | N86: =IF(G86=1,0.2*R86/F86,N85) | O86: =IF(G86=1,R86*(1-1.0),IF(H85=0,1,O85*(1+0.00023125256064071564))) | P86: =IF(G86=1,IF(H85=0,1,ABS(0.2-J85*B86/I86)+ABS(0.2-K85*C86/I86)+ABS(0.2-L85*D86/I86)+ABS(0.2-M85*E86/I86)+ABS(0.2-N85*F86/I86)),0) | Q86: =P86*0.0015 | R86: =I86*(1-Q86) | S86: =R86/R85-1 | T86: =MAX(T85,R86) | U86: =R86/T86-1 | V86: 1.1992069 | W86: =R86-V86
A87: 38565 | B87: =Prices!B87 | C87: =Prices!C87 | D87: =Prices!D87 | E87: =Prices!E87 | F87: =Prices!F87 | G87: =IF(AND(85>=16,TEXT(A87,"yyyy-mm")<>TEXT(A88,"yyyy-mm")),1,0) | H87: =IF(OR(H86=1,G87=1),1,0) | I87: =IF(H86=0,1,SUMPRODUCT(J86:N86,B87:F87)+O86*(1+0.00023125256064071564)) | J87: =IF(G87=1,0.2*R87/B87,J86) | K87: =IF(G87=1,0.2*R87/C87,K86) | L87: =IF(G87=1,0.2*R87/D87,L86) | M87: =IF(G87=1,0.2*R87/E87,M86) | N87: =IF(G87=1,0.2*R87/F87,N86) | O87: =IF(G87=1,R87*(1-1.0),IF(H86=0,1,O86*(1+0.00023125256064071564))) | P87: =IF(G87=1,IF(H86=0,1,ABS(0.2-J86*B87/I87)+ABS(0.2-K86*C87/I87)+ABS(0.2-L86*D87/I87)+ABS(0.2-M86*E87/I87)+ABS(0.2-N86*F87/I87)),0) | Q87: =P87*0.0015 | R87: =I87*(1-Q87) | S87: =R87/R86-1 | T87: =MAX(T86,R87) | U87: =R87/T87-1 | V87: 1.207975 | W87: =R87-V87
A88: 38566 | B88: =Prices!B88 | C88: =Prices!C88 | D88: =Prices!D88 | E88: =Prices!E88 | F88: =Prices!F88 | G88: =IF(AND(86>=16,TEXT(A88,"yyyy-mm")<>TEXT(A89,"yyyy-mm")),1,0) | H88: =IF(OR(H87=1,G88=1),1,0) | I88: =IF(H87=0,1,SUMPRODUCT(J87:N87,B88:F88)+O87*(1+0.00023125256064071564)) | J88: =IF(G88=1,0.2*R88/B88,J87) | K88: =IF(G88=1,0.2*R88/C88,K87) | L88: =IF(G88=1,0.2*R88/D88,L87) | M88: =IF(G88=1,0.2*R88/E88,M87) | N88: =IF(G88=1,0.2*R88/F88,N87) | O88: =IF(G88=1,R88*(1-1.0),IF(H87=0,1,O87*(1+0.00023125256064071564))) | P88: =IF(G88=1,IF(H87=0,1,ABS(0.2-J87*B88/I88)+ABS(0.2-K87*C88/I88)+ABS(0.2-L87*D88/I88)+ABS(0.2-M87*E88/I88)+ABS(0.2-N87*F88/I88)),0) | Q88: =P88*0.0015 | R88: =I88*(1-Q88) | S88: =R88/R87-1 | T88: =MAX(T87,R88) | U88: =R88/T88-1 | V88: 1.2352279 | W88: =R88-V88
A89: 38567 | B89: =Prices!B89 | C89: =Prices!C89 | D89: =Prices!D89 | E89: =Prices!E89 | F89: =Prices!F89 | G89: =IF(AND(87>=16,TEXT(A89,"yyyy-mm")<>TEXT(A90,"yyyy-mm")),1,0) | H89: =IF(OR(H88=1,G89=1),1,0) | I89: =IF(H88=0,1,SUMPRODUCT(J88:N88,B89:F89)+O88*(1+0.00023125256064071564)) | J89: =IF(G89=1,0.2*R89/B89,J88) | K89: =IF(G89=1,0.2*R89/C89,K88) | L89: =IF(G89=1,0.2*R89/D89,L88) | M89: =IF(G89=1,0.2*R89/E89,M88) | N89: =IF(G89=1,0.2*R89/F89,N88) | O89: =IF(G89=1,R89*(1-1.0),IF(H88=0,1,O88*(1+0.00023125256064071564))) | P89: =IF(G89=1,IF(H88=0,1,ABS(0.2-J88*B89/I89)+ABS(0.2-K88*C89/I89)+ABS(0.2-L88*D89/I89)+ABS(0.2-M88*E89/I89)+ABS(0.2-N88*F89/I89)),0) | Q89: =P89*0.0015 | R89: =I89*(1-Q89) | S89: =R89/R88-1 | T89: =MAX(T88,R89) | U89: =R89/T89-1 | V89: 1.2370935 | W89: =R89-V89
A90: 38568 | B90: =Prices!B90 | C90: =Prices!C90 | D90: =Prices!D90 | E90: =Prices!E90 | F90: =Prices!F90 | G90: =IF(AND(88>=16,TEXT(A90,"yyyy-mm")<>TEXT(A91,"yyyy-mm")),1,0) | H90: =IF(OR(H89=1,G90=1),1,0) | I90: =IF(H89=0,1,SUMPRODUCT(J89:N89,B90:F90)+O89*(1+0.00023125256064071564)) | J90: =IF(G90=1,0.2*R90/B90,J89) | K90: =IF(G90=1,0.2*R90/C90,K89) | L90: =IF(G90=1,0.2*R90/D90,L89) | M90: =IF(G90=1,0.2*R90/E90,M89) | N90: =IF(G90=1,0.2*R90/F90,N89) | O90: =IF(G90=1,R90*(1-1.0),IF(H89=0,1,O89*(1+0.00023125256064071564))) | P90: =IF(G90=1,IF(H89=0,1,ABS(0.2-J89*B90/I90)+ABS(0.2-K89*C90/I90)+ABS(0.2-L89*D90/I90)+ABS(0.2-M89*E90/I90)+ABS(0.2-N89*F90/I90)),0) | Q90: =P90*0.0015 | R90: =I90*(1-Q90) | S90: =R90/R89-1 | T90: =MAX(T89,R90) | U90: =R90/T90-1 | V90: 1.2464002 | W90: =R90-V90
A91: 38569 | B91: =Prices!B91 | C91: =Prices!C91 | D91: =Prices!D91 | E91: =Prices!E91 | F91: =Prices!F91 | G91: =IF(AND(89>=16,TEXT(A91,"yyyy-mm")<>TEXT(A92,"yyyy-mm")),1,0) | H91: =IF(OR(H90=1,G91=1),1,0) | I91: =IF(H90=0,1,SUMPRODUCT(J90:N90,B91:F91)+O90*(1+0.00023125256064071564)) | J91: =IF(G91=1,0.2*R91/B91,J90) | K91: =IF(G91=1,0.2*R91/C91,K90) | L91: =IF(G91=1,0.2*R91/D91,L90) | M91: =IF(G91=1,0.2*R91/E91,M90) | N91: =IF(G91=1,0.2*R91/F91,N90) | O91: =IF(G91=1,R91*(1-1.0),IF(H90=0,1,O90*(1+0.00023125256064071564))) | P91: =IF(G91=1,IF(H90=0,1,ABS(0.2-J90*B91/I91)+ABS(0.2-K90*C91/I91)+ABS(0.2-L90*D91/I91)+ABS(0.2-M90*E91/I91)+ABS(0.2-N90*F91/I91)),0) | Q91: =P91*0.0015 | R91: =I91*(1-Q91) | S91: =R91/R90-1 | T91: =MAX(T90,R91) | U91: =R91/T91-1 | V91: 1.2531536 | W91: =R91-V91
A92: 38572 | B92: =Prices!B92 | C92: =Prices!C92 | D92: =Prices!D92 | E92: =Prices!E92 | F92: =Prices!F92 | G92: =IF(AND(90>=16,TEXT(A92,"yyyy-mm")<>TEXT(A93,"yyyy-mm")),1,0) | H92: =IF(OR(H91=1,G92=1),1,0) | I92: =IF(H91=0,1,SUMPRODUCT(J91:N91,B92:F92)+O91*(1+0.00023125256064071564)) | J92: =IF(G92=1,0.2*R92/B92,J91) | K92: =IF(G92=1,0.2*R92/C92,K91) | L92: =IF(G92=1,0.2*R92/D92,L91) | M92: =IF(G92=1,0.2*R92/E92,M91) | N92: =IF(G92=1,0.2*R92/F92,N91) | O92: =IF(G92=1,R92*(1-1.0),IF(H91=0,1,O91*(1+0.00023125256064071564))) | P92: =IF(G92=1,IF(H91=0,1,ABS(0.2-J91*B92/I92)+ABS(0.2-K91*C92/I92)+ABS(0.2-L91*D92/I92)+ABS(0.2-M91*E92/I92)+ABS(0.2-N91*F92/I92)),0) | Q92: =P92*0.0015 | R92: =I92*(1-Q92) | S92: =R92/R91-1 | T92: =MAX(T91,R92) | U92: =R92/T92-1 | V92: 1.233619 | W92: =R92-V92
A93: 38573 | B93: =Prices!B93 | C93: =Prices!C93 | D93: =Prices!D93 | E93: =Prices!E93 | F93: =Prices!F93 | G93: =IF(AND(91>=16,TEXT(A93,"yyyy-mm")<>TEXT(A94,"yyyy-mm")),1,0) | H93: =IF(OR(H92=1,G93=1),1,0) | I93: =IF(H92=0,1,SUMPRODUCT(J92:N92,B93:F93)+O92*(1+0.00023125256064071564)) | J93: =IF(G93=1,0.2*R93/B93,J92) | K93: =IF(G93=1,0.2*R93/C93,K92) | L93: =IF(G93=1,0.2*R93/D93,L92) | M93: =IF(G93=1,0.2*R93/E93,M92) | N93: =IF(G93=1,0.2*R93/F93,N92) | O93: =IF(G93=1,R93*(1-1.0),IF(H92=0,1,O92*(1+0.00023125256064071564))) | P93: =IF(G93=1,IF(H92=0,1,ABS(0.2-J92*B93/I93)+ABS(0.2-K92*C93/I93)+ABS(0.2-L92*D93/I93)+ABS(0.2-M92*E93/I93)+ABS(0.2-N92*F93/I93)),0) | Q93: =P93*0.0015 | R93: =I93*(1-Q93) | S93: =R93/R92-1 | T93: =MAX(T92,R93) | U93: =R93/T93-1 | V93: 1.229664 | W93: =R93-V93
A94: 38574 | B94: =Prices!B94 | C94: =Prices!C94 | D94: =Prices!D94 | E94: =Prices!E94 | F94: =Prices!F94 | G94: =IF(AND(92>=16,TEXT(A94,"yyyy-mm")<>TEXT(A95,"yyyy-mm")),1,0) | H94: =IF(OR(H93=1,G94=1),1,0) | I94: =IF(H93=0,1,SUMPRODUCT(J93:N93,B94:F94)+O93*(1+0.00023125256064071564)) | J94: =IF(G94=1,0.2*R94/B94,J93) | K94: =IF(G94=1,0.2*R94/C94,K93) | L94: =IF(G94=1,0.2*R94/D94,L93) | M94: =IF(G94=1,0.2*R94/E94,M93) | N94: =IF(G94=1,0.2*R94/F94,N93) | O94: =IF(G94=1,R94*(1-1.0),IF(H93=0,1,O93*(1+0.00023125256064071564))) | P94: =IF(G94=1,IF(H93=0,1,ABS(0.2-J93*B94/I94)+ABS(0.2-K93*C94/I94)+ABS(0.2-L93*D94/I94)+ABS(0.2-M93*E94/I94)+ABS(0.2-N93*F94/I94)),0) | Q94: =P94*0.0015 | R94: =I94*(1-Q94) | S94: =R94/R93-1 | T94: =MAX(T93,R94) | U94: =R94/T94-1 | V94: 1.2564706 | W94: =R94-V94
A95: 38575 | B95: =Prices!B95 | C95: =Prices!C95 | D95: =Prices!D95 | E95: =Prices!E95 | F95: =Prices!F95 | G95: =IF(AND(93>=16,TEXT(A95,"yyyy-mm")<>TEXT(A96,"yyyy-mm")),1,0) | H95: =IF(OR(H94=1,G95=1),1,0) | I95: =IF(H94=0,1,SUMPRODUCT(J94:N94,B95:F95)+O94*(1+0.00023125256064071564)) | J95: =IF(G95=1,0.2*R95/B95,J94) | K95: =IF(G95=1,0.2*R95/C95,K94) | L95: =IF(G95=1,0.2*R95/D95,L94) | M95: =IF(G95=1,0.2*R95/E95,M94) | N95: =IF(G95=1,0.2*R95/F95,N94) | O95: =IF(G95=1,R95*(1-1.0),IF(H94=0,1,O94*(1+0.00023125256064071564))) | P95: =IF(G95=1,IF(H94=0,1,ABS(0.2-J94*B95/I95)+ABS(0.2-K94*C95/I95)+ABS(0.2-L94*D95/I95)+ABS(0.2-M94*E95/I95)+ABS(0.2-N94*F95/I95)),0) | Q95: =P95*0.0015 | R95: =I95*(1-Q95) | S95: =R95/R94-1 | T95: =MAX(T94,R95) | U95: =R95/T95-1 | V95: 1.2692768 | W95: =R95-V95
A96: 38576 | B96: =Prices!B96 | C96: =Prices!C96 | D96: =Prices!D96 | E96: =Prices!E96 | F96: =Prices!F96 | G96: =IF(AND(94>=16,TEXT(A96,"yyyy-mm")<>TEXT(A97,"yyyy-mm")),1,0) | H96: =IF(OR(H95=1,G96=1),1,0) | I96: =IF(H95=0,1,SUMPRODUCT(J95:N95,B96:F96)+O95*(1+0.00023125256064071564)) | J96: =IF(G96=1,0.2*R96/B96,J95) | K96: =IF(G96=1,0.2*R96/C96,K95) | L96: =IF(G96=1,0.2*R96/D96,L95) | M96: =IF(G96=1,0.2*R96/E96,M95) | N96: =IF(G96=1,0.2*R96/F96,N95) | O96: =IF(G96=1,R96*(1-1.0),IF(H95=0,1,O95*(1+0.00023125256064071564))) | P96: =IF(G96=1,IF(H95=0,1,ABS(0.2-J95*B96/I96)+ABS(0.2-K95*C96/I96)+ABS(0.2-L95*D96/I96)+ABS(0.2-M95*E96/I96)+ABS(0.2-N95*F96/I96)),0) | Q96: =P96*0.0015 | R96: =I96*(1-Q96) | S96: =R96/R95-1 | T96: =MAX(T95,R96) | U96: =R96/T96-1 | V96: 1.2737728 | W96: =R96-V96
A97: 38580 | B97: =Prices!B97 | C97: =Prices!C97 | D97: =Prices!D97 | E97: =Prices!E97 | F97: =Prices!F97 | G97: =IF(AND(95>=16,TEXT(A97,"yyyy-mm")<>TEXT(A98,"yyyy-mm")),1,0) | H97: =IF(OR(H96=1,G97=1),1,0) | I97: =IF(H96=0,1,SUMPRODUCT(J96:N96,B97:F97)+O96*(1+0.00023125256064071564)) | J97: =IF(G97=1,0.2*R97/B97,J96) | K97: =IF(G97=1,0.2*R97/C97,K96) | L97: =IF(G97=1,0.2*R97/D97,L96) | M97: =IF(G97=1,0.2*R97/E97,M96) | N97: =IF(G97=1,0.2*R97/F97,N96) | O97: =IF(G97=1,R97*(1-1.0),IF(H96=0,1,O96*(1+0.00023125256064071564))) | P97: =IF(G97=1,IF(H96=0,1,ABS(0.2-J96*B97/I97)+ABS(0.2-K96*C97/I97)+ABS(0.2-L96*D97/I97)+ABS(0.2-M96*E97/I97)+ABS(0.2-N96*F97/I97)),0) | Q97: =P97*0.0015 | R97: =I97*(1-Q97) | S97: =R97/R96-1 | T97: =MAX(T96,R97) | U97: =R97/T97-1 | V97: 1.2837911 | W97: =R97-V97
A98: 38581 | B98: =Prices!B98 | C98: =Prices!C98 | D98: =Prices!D98 | E98: =Prices!E98 | F98: =Prices!F98 | G98: =IF(AND(96>=16,TEXT(A98,"yyyy-mm")<>TEXT(A99,"yyyy-mm")),1,0) | H98: =IF(OR(H97=1,G98=1),1,0) | I98: =IF(H97=0,1,SUMPRODUCT(J97:N97,B98:F98)+O97*(1+0.00023125256064071564)) | J98: =IF(G98=1,0.2*R98/B98,J97) | K98: =IF(G98=1,0.2*R98/C98,K97) | L98: =IF(G98=1,0.2*R98/D98,L97) | M98: =IF(G98=1,0.2*R98/E98,M97) | N98: =IF(G98=1,0.2*R98/F98,N97) | O98: =IF(G98=1,R98*(1-1.0),IF(H97=0,1,O97*(1+0.00023125256064071564))) | P98: =IF(G98=1,IF(H97=0,1,ABS(0.2-J97*B98/I98)+ABS(0.2-K97*C98/I98)+ABS(0.2-L97*D98/I98)+ABS(0.2-M97*E98/I98)+ABS(0.2-N97*F98/I98)),0) | Q98: =P98*0.0015 | R98: =I98*(1-Q98) | S98: =R98/R97-1 | T98: =MAX(T97,R98) | U98: =R98/T98-1 | V98: 1.2979961 | W98: =R98-V98
A99: 38582 | B99: =Prices!B99 | C99: =Prices!C99 | D99: =Prices!D99 | E99: =Prices!E99 | F99: =Prices!F99 | G99: =IF(AND(97>=16,TEXT(A99,"yyyy-mm")<>TEXT(A100,"yyyy-mm")),1,0) | H99: =IF(OR(H98=1,G99=1),1,0) | I99: =IF(H98=0,1,SUMPRODUCT(J98:N98,B99:F99)+O98*(1+0.00023125256064071564)) | J99: =IF(G99=1,0.2*R99/B99,J98) | K99: =IF(G99=1,0.2*R99/C99,K98) | L99: =IF(G99=1,0.2*R99/D99,L98) | M99: =IF(G99=1,0.2*R99/E99,M98) | N99: =IF(G99=1,0.2*R99/F99,N98) | O99: =IF(G99=1,R99*(1-1.0),IF(H98=0,1,O98*(1+0.00023125256064071564))) | P99: =IF(G99=1,IF(H98=0,1,ABS(0.2-J98*B99/I99)+ABS(0.2-K98*C99/I99)+ABS(0.2-L98*D99/I99)+ABS(0.2-M98*E99/I99)+ABS(0.2-N98*F99/I99)),0) | Q99: =P99*0.0015 | R99: =I99*(1-Q99) | S99: =R99/R98-1 | T99: =MAX(T98,R99) | U99: =R99/T99-1 | V99: 1.2892538 | W99: =R99-V99
A100: 38583 | B100: =Prices!B100 | C100: =Prices!C100 | D100: =Prices!D100 | E100: =Prices!E100 | F100: =Prices!F100 | G100: =IF(AND(98>=16,TEXT(A100,"yyyy-mm")<>TEXT(A101,"yyyy-mm")),1,0) | H100: =IF(OR(H99=1,G100=1),1,0) | I100: =IF(H99=0,1,SUMPRODUCT(J99:N99,B100:F100)+O99*(1+0.00023125256064071564)) | J100: =IF(G100=1,0.2*R100/B100,J99) | K100: =IF(G100=1,0.2*R100/C100,K99) | L100: =IF(G100=1,0.2*R100/D100,L99) | M100: =IF(G100=1,0.2*R100/E100,M99) | N100: =IF(G100=1,0.2*R100/F100,N99) | O100: =IF(G100=1,R100*(1-1.0),IF(H99=0,1,O99*(1+0.00023125256064071564))) | P100: =IF(G100=1,IF(H99=0,1,ABS(0.2-J99*B100/I100)+ABS(0.2-K99*C100/I100)+ABS(0.2-L99*D100/I100)+ABS(0.2-M99*E100/I100)+ABS(0.2-N99*F100/I100)),0) | Q100: =P100*0.0015 | R100: =I100*(1-Q100) | S100: =R100/R99-1 | T100: =MAX(T99,R100) | U100: =R100/T100-1 | V100: 1.2909923 | W100: =R100-V100
...

Sheet Metrics
A1: Metric | B1: Excel (live formula) | C1: Note
A2: Final NAV | B2: =Backtest!R5257 | C2: grew from 1.00
A3: CAGR | B3: =(Backtest!R5257/Backtest!R2)^(1/((Backtest!A5257-Backtest!A2)/365.25))-1
A4: Annualised volatility | B4: =STDEV.S(Backtest!S2:S5257)*SQRT(252) | C4: sample sd x sqrt(252)
A5: Max drawdown | B5: =-MIN(Backtest!U2:U5257)
A6: Compounded cash return (CAGR) | B6: =((1+0.00023125256064071564)^(5256/((Backtest!A5257-Backtest!A2)/365.25))-1) | C6: flat proxy -- see READ ME
A7: Sharpe (geometric, paper definition) | B7: =(B3-B6)/B4 | C7: (CAGR - cash) / vol
A8: Sharpe (conventional) | B8: =(AVERAGE(Backtest!S2:S5257)-0.00023125256064071564)/STDEV.S(Backtest!S2:S5257)*SQRT(252) | C8: mean excess / sd
A9: Total cost paid (fraction of NAV) | B9: =SUM(Backtest!Q2:Q5257)
A10: Total turnover (one-way) | B10: =SUM(Backtest!P2:P5257)/2
A11: Number of rebalances | B11: =SUM(Backtest!G2:G5257)
A13: LARGEST NAV DIFFERENCE vs engine | B13: =MAX(MAX(Backtest!W2:W5257),-MIN(Backtest!W2:W5257)) | C13: should be ~1e-15
